Workbook

Sheet Summary
A1: Regulus AI Acceptance Benchmark REV02 (300Q): Test Results
A2: Every question carries an explicit result in Detailed Results, scored question by question against the workbook's own rubric (columns L-Q) and against the regulation text in the read-only eCFR snapshot - not against the draft key alone. Where the draft key is itself wrong, the answer was judged against the regulation and the discrepancy is recorded in Evaluator Notes. The key remains unverified by an SME (0 of 300 rows marked Y in column K), so these results are an independent reviewer's scoring, not a signed-off contractual acceptance result: an SME should countersign before the gates are treated as final.
A3: Metric | B3: Value
A4: Total questions | B4: 300
A5: Questions successfully tested | B5: =COUNTIF('Detailed Results'!$L$2:$L$301,"OK")
A6: Questions failed to execute (ERROR) | B6: =COUNTIF('Detailed Results'!$M$2:$M$301,"ERROR")
A7: Questions not tested | B7: =COUNTIF('Detailed Results'!$M$2:$M$301,"NOT TESTED")
A8: Questions passed | B8: =COUNTIF('Detailed Results'!$M$2:$M$301,"PASS")
A9: Questions failed | B9: =COUNTIF('Detailed Results'!$M$2:$M$301,"FAIL")
A10: Questions requiring SME review | B10: =COUNTIF('Detailed Results'!$M$2:$M$301,"REQUIRES SME REVIEW")
A11: Pass rate % (PASS / (PASS+FAIL)) | B11: =IF(B8+B9=0,"Not determinable (no rows scored)",B8/(B8+B9))
A12: Fail rate % (FAIL / (PASS+FAIL)) | B12: =IF(B8+B9=0,"Not determinable (no rows scored)",B9/(B8+B9))
A13: Execution error rate % (ERROR / total) | B13: =B6/B4
A14: Execution success rate % (tested / total) | B14: =B5/B4
A15: SME review rate % (REQUIRES SME REVIEW / total) | B15: =B10/B4
A16: Average response time (s), executed rows | B16: =AVERAGEIF('Detailed Results'!$L$2:$L$301,"OK",'Detailed Results'!$K$2:$K$301)
A17: Median response time (s), executed rows (computed in Python from column K; no conditional-median formula) | B17: 14.79
A18: Rows flagged borderline for an SME second look | B18: =COUNTIF('Detailed Results'!$Q$2:$Q$301,"Y")
A19: Answers with partial credit (see Partially Correct sheet) | B19: =COUNTIFS('Detailed Results'!$M$2:$M$301,"FAIL",'Detailed Results'!$T$2:$T$301,">=1")+COUNTIFS('Detailed Results'!$M$2:$M$301,"FAIL",'Detailed Results'!$T$2:$T$301,"0",'Detailed Results'!$U$2:$U$301,">=1")
A20: of those, substance fully correct, blocked on another dimension | B20: =COUNTIFS('Detailed Results'!$M$2:$M$301,"FAIL",'Detailed Results'!$T$2:$T$301,2)
A21: of those, directionally right but materially incomplete | B21: =COUNTIFS('Detailed Results'!$M$2:$M$301,"FAIL",'Detailed Results'!$T$2:$T$301,1)
A22: Answers with no partial credit (substance and completeness both 0) | B22: =COUNTIFS('Detailed Results'!$M$2:$M$301,"FAIL",'Detailed Results'!$T$2:$T$301,0,'Detailed Results'!$U$2:$U$301,0)
A24: Test date/time (UTC) | B24: 2026-10-01T08:40:00+00:00 to 2026-10-01T11:41:13+00:00
A25: Model/checkpoint | B25: Qwen/Qwen3-0.6B @ c1899de289a04d12100db370d81485cdf75e47ca (base model, no adapter; weights sha256 f47f71177f32bcd101b7573ec9171e6a57f4f4d31148d38e382306f42996874b)
A26: Git commit/version | B26: 800af071e1067db4b4f9d31dd5c0309f7fb2589d (working tree had uncommitted files: the test scripts)
A27: Test environment | B27: macOS-26.1-arm64-arm-64bit; device cpu, dtype float32; Apple M2, 8 GB; read-only PostgreSQL eCFR snapshot
A28: Benchmark file / sha256 before → after | B28: Regulus_AI_Acceptance_Benchmark_REV02_300Q.xlsx / c009d5f9c649822097b02a6c6aba415715fb0929914ef452acb03c8c3ac4a110 → c009d5f9c649822097b02a6c6aba415715fb0929914ef452acb03c8c3ac4a110 (now c009d5f9c649822097b02a6c6aba415715fb0929914ef452acb03c8c3ac4a110)
A30: ACCEPTANCE GATES (computed from rubric columns R-W of Detailed Results) | B30: Scored by an independent reviewer against the regulation text; the answer key itself remains unverified, so an SME must countersign before these are treated as final.
A31: Gate / metric | B31: Result | C31: Threshold | D31: Status | E31: Scored on
A32: G1 Citation accuracy | B32: =SUM('Detailed Results'!$R$2:$R$301)/COUNT('Detailed Results'!$R$2:$R$301) | C32: 99% | D32: =IF(B32>=0.99,"PASS","FAIL") | E32: every scored row, rubric L
A33: G2 Fabricated citations (count) | B33: =SUM('Detailed Results'!$S$2:$S$301) | C33: =0 | D33: =IF(B33<=0,"PASS","FAIL") | E33: every scored row, rubric M
A34: G3 Negative control pass rate | B34: =SUMIFS('Detailed Results'!$R$2:$R$301,'Detailed Results'!$C$2:$C$301,"Negative Control")/COUNTIFS('Detailed Results'!$C$2:$C$301,"Negative Control") | C34: 100% | D34: =IF(B34=1.0,"PASS","FAIL") | E34: the 22 Negative Control rows, rubric L
A35: G4 Substantive correctness | B35: =SUM('Detailed Results'!$T$2:$T$301)/(2*COUNT('Detailed Results'!$T$2:$T$301)) | C35: 95% | D35: =IF(B35>=0.95,"PASS","FAIL") | E35: points out of maximum, rubric N
A36: G5 Completeness | B36: =SUM('Detailed Results'!$U$2:$U$301)/(2*COUNT('Detailed Results'!$U$2:$U$301)) | C36: 90% | D36: =IF(B36>=0.9,"PASS","FAIL") | E36: points out of maximum, rubric O
A37: G6 Scope discipline | B37: =SUM('Detailed Results'!$V$2:$V$301)/COUNT('Detailed Results'!$V$2:$V$301) | C37: 98% | D37: =IF(B37>=0.98,"PASS","FAIL") | E37: every scored row, rubric P
A38: G7 ISO 13485 clause concordance | B38: =SUM('Detailed Results'!$W$2:$W$301)/COUNT('Detailed Results'!$W$2:$W$301) | C38: 95% | D38: =IF(B38>=0.95,"PASS","FAIL") | E38: rows carrying an ISO clause key, rubric Q
A39: OVERALL ACCEPTANCE (all seven gates must read PASS) | B39: =IF(COUNTIF(D32:D38,"FAIL")=0,"PASS","FAIL")
A40: Answer key verification (benchmark column K) | B40: 0 of 300 rows marked Y - WARNING, key not SME-verified
A42: Breakdown by category (Domain, col B)
A43: Category | B43: Total | C43: Tested | D43: Passed | E43: Failed | F43: Errors | G43: SME review | H43: Flagged (indicator)
A44: Dietary Supplements — 21 CFR 111 | B44: =COUNTIF('Detailed Results'!$B$2:$B$301,$A44) | C44: =COUNTIFS('Detailed Results'!$B$2:$B$301,$A44,'Detailed Results'!$L$2:$L$301,"OK") | D44: =COUNTIFS('Detailed Results'!$B$2:$B$301,$A44,'Detailed Results'!$M$2:$M$301,"PASS") | E44: =COUNTIFS('Detailed Results'!$B$2:$B$301,$A44,'Detailed Results'!$M$2:$M$301,"FAIL") | F44: =COUNTIFS('Detailed Results'!$B$2:$B$301,$A44,'Detailed Results'!$M$2:$M$301,"ERROR") | G44: =COUNTIFS('Detailed Results'!$B$2:$B$301,$A44,'Detailed Results'!$M$2:$M$301,"REQUIRES SME REVIEW") | H44: =COUNTIFS('Detailed Results'!$B$2:$B$301,$A44,'Detailed Results'!$Q$2:$Q$301,"Y")
A45: Human Food — 21 CFR 117 | B45: =COUNTIF('Detailed Results'!$B$2:$B$301,$A45) | C45: =COUNTIFS('Detailed Results'!$B$2:$B$301,$A45,'Detailed Results'!$L$2:$L$301,"OK") | D45: =COUNTIFS('Detailed Results'!$B$2:$B$301,$A45,'Detailed Results'!$M$2:$M$301,"PASS") | E45: =COUNTIFS('Detailed Results'!$B$2:$B$301,$A45,'Detailed Results'!$M$2:$M$301,"FAIL") | F45: =COUNTIFS('Detailed Results'!$B$2:$B$301,$A45,'Detailed Results'!$M$2:$M$301,"ERROR") | G45: =COUNTIFS('Detailed Results'!$B$2:$B$301,$A45,'Detailed Results'!$M$2:$M$301,"REQUIRES SME REVIEW") | H45: =COUNTIFS('Detailed Results'!$B$2:$B$301,$A45,'Detailed Results'!$Q$2:$Q$301,"Y")
A46: Food Labeling — 21 CFR 101 | B46: =COUNTIF('Detailed Results'!$B$2:$B$301,$A46) | C46: =COUNTIFS('Detailed Results'!$B$2:$B$301,$A46,'Detailed Results'!$L$2:$L$301,"OK") | D46: =COUNTIFS('Detailed Results'!$B$2:$B$301,$A46,'Detailed Results'!$M$2:$M$301,"PASS") | E46: =COUNTIFS('Detailed Results'!$B$2:$B$301,$A46,'Detailed Results'!$M$2:$M$301,"FAIL") | F46: =COUNTIFS('Detailed Results'!$B$2:$B$301,$A46,'Detailed Results'!$M$2:$M$301,"ERROR") | G46: =COUNTIFS('Detailed Results'!$B$2:$B$301,$A46,'Detailed Results'!$M$2:$M$301,"REQUIRES SME REVIEW") | H46: =COUNTIFS('Detailed Results'!$B$2:$B$301,$A46,'Detailed Results'!$Q$2:$Q$301,"Y")
A47: Drug CGMP — 21 CFR 210/211 | B47: =COUNTIF('Detailed Results'!$B$2:$B$301,$A47) | C47: =COUNTIFS('Detailed Results'!$B$2:$B$301,$A47,'Detailed Results'!$L$2:$L$301,"OK") | D47: =COUNTIFS('Detailed Results'!$B$2:$B$301,$A47,'Detailed Results'!$M$2:$M$301,"PASS") | E47: =COUNTIFS('Detailed Results'!$B$2:$B$301,$A47,'Detailed Results'!$M$2:$M$301,"FAIL") | F47: =COUNTIFS('Detailed Results'!$B$2:$B$301,$A47,'Detailed Results'!$M$2:$M$301,"ERROR") | G47: =COUNTIFS('Detailed Results'!$B$2:$B$301,$A47,'Detailed Results'!$M$2:$M$301,"REQUIRES SME REVIEW") | H47: =COUNTIFS('Detailed Results'!$B$2:$B$301,$A47,'Detailed Results'!$Q$2:$Q$301,"Y")
A48: Medical Devices — 21 CFR 820 / QMSR | B48: =COUNTIF('Detailed Results'!$B$2:$B$301,$A48) | C48: =COUNTIFS('Detailed Results'!$B$2:$B$301,$A48,'Detailed Results'!$L$2:$L$301,"OK") | D48: =COUNTIFS('Detailed Results'!$B$2:$B$301,$A48,'Detailed Results'!$M$2:$M$301,"PASS") | E48: =COUNTIFS('Detailed Results'!$B$2:$B$301,$A48,'Detailed Results'!$M$2:$M$301,"FAIL") | F48: =COUNTIFS('Detailed Results'!$B$2:$B$301,$A48,'Detailed Results'!$M$2:$M$301,"ERROR") | G48: =COUNTIFS('Detailed Results'!$B$2:$B$301,$A48,'Detailed Results'!$M$2:$M$301,"REQUIRES SME REVIEW") | H48: =COUNTIFS('Detailed Results'!$B$2:$B$301,$A48,'Detailed Results'!$Q$2:$Q$301,"Y")
A49: Electronic Records — 21 CFR 11 | B49: =COUNTIF('Detailed Results'!$B$2:$B$301,$A49) | C49: =COUNTIFS('Detailed Results'!$B$2:$B$301,$A49,'Detailed Results'!$L$2:$L$301,"OK") | D49: =COUNTIFS('Detailed Results'!$B$2:$B$301,$A49,'Detailed Results'!$M$2:$M$301,"PASS") | E49: =COUNTIFS('Detailed Results'!$B$2:$B$301,$A49,'Detailed Results'!$M$2:$M$301,"FAIL") | F49: =COUNTIFS('Detailed Results'!$B$2:$B$301,$A49,'Detailed Results'!$M$2:$M$301,"ERROR") | G49: =COUNTIFS('Detailed Results'!$B$2:$B$301,$A49,'Detailed Results'!$M$2:$M$301,"REQUIRES SME REVIEW") | H49: =COUNTIFS('Detailed Results'!$B$2:$B$301,$A49,'Detailed Results'!$Q$2:$Q$301,"Y")
A50: FSVP — 21 CFR 1 Subpart L | B50: =COUNTIF('Detailed Results'!$B$2:$B$301,$A50) | C50: =COUNTIFS('Detailed Results'!$B$2:$B$301,$A50,'Detailed Results'!$L$2:$L$301,"OK") | D50: =COUNTIFS('Detailed Results'!$B$2:$B$301,$A50,'Detailed Results'!$M$2:$M$301,"PASS") | E50: =COUNTIFS('Detailed Results'!$B$2:$B$301,$A50,'Detailed Results'!$M$2:$M$301,"FAIL") | F50: =COUNTIFS('Detailed Results'!$B$2:$B$301,$A50,'Detailed Results'!$M$2:$M$301,"ERROR") | G50: =COUNTIFS('Detailed Results'!$B$2:$B$301,$A50,'Detailed Results'!$M$2:$M$301,"REQUIRES SME REVIEW") | H50: =COUNTIFS('Detailed Results'!$B$2:$B$301,$A50,'Detailed Results'!$Q$2:$Q$301,"Y")
A51: Device Submissions — 21 CFR 807/814/812/860 | B51: =COUNTIF('Detailed Results'!$B$2:$B$301,$A51) | C51: =COUNTIFS('Detailed Results'!$B$2:$B$301,$A51,'Detailed Results'!$L$2:$L$301,"OK") | D51: =COUNTIFS('Detailed Results'!$B$2:$B$301,$A51,'Detailed Results'!$M$2:$M$301,"PASS") | E51: =COUNTIFS('Detailed Results'!$B$2:$B$301,$A51,'Detailed Results'!$M$2:$M$301,"FAIL") | F51: =COUNTIFS('Detailed Results'!$B$2:$B$301,$A51,'Detailed Results'!$M$2:$M$301,"ERROR") | G51: =COUNTIFS('Detailed Results'!$B$2:$B$301,$A51,'Detailed Results'!$M$2:$M$301,"REQUIRES SME REVIEW") | H51: =COUNTIFS('Detailed Results'!$B$2:$B$301,$A51,'Detailed Results'!$Q$2:$Q$301,"Y")
A52: Device Postmarket — 21 CFR 803/806/7 | B52: =COUNTIF('Detailed Results'!$B$2:$B$301,$A52) | C52: =COUNTIFS('Detailed Results'!$B$2:$B$301,$A52,'Detailed Results'!$L$2:$L$301,"OK") | D52: =COUNTIFS('Detailed Results'!$B$2:$B$301,$A52,'Detailed Results'!$M$2:$M$301,"PASS") | E52: =COUNTIFS('Detailed Results'!$B$2:$B$301,$A52,'Detailed Results'!$M$2:$M$301,"FAIL") | F52: =COUNTIFS('Detailed Results'!$B$2:$B$301,$A52,'Detailed Results'!$M$2:$M$301,"ERROR") | G52: =COUNTIFS('Detailed Results'!$B$2:$B$301,$A52,'Detailed Results'!$M$2:$M$301,"REQUIRES SME REVIEW") | H52: =COUNTIFS('Detailed Results'!$B$2:$B$301,$A52,'Detailed Results'!$Q$2:$Q$301,"Y")
A53: Tobacco & ENDS — 21 CFR 1100-1150 | B53: =COUNTIF('Detailed Results'!$B$2:$B$301,$A53) | C53: =COUNTIFS('Detailed Results'!$B$2:$B$301,$A53,'Detailed Results'!$L$2:$L$301,"OK") | D53: =COUNTIFS('Detailed Results'!$B$2:$B$301,$A53,'Detailed Results'!$M$2:$M$301,"PASS") | E53: =COUNTIFS('Detailed Results'!$B$2:$B$301,$A53,'Detailed Results'!$M$2:$M$301,"FAIL") | F53: =COUNTIFS('Detailed Results'!$B$2:$B$301,$A53,'Detailed Results'!$M$2:$M$301,"ERROR") | G53: =COUNTIFS('Detailed Results'!$B$2:$B$301,$A53,'Detailed Results'!$M$2:$M$301,"REQUIRES SME REVIEW") | H53: =COUNTIFS('Detailed Results'!$B$2:$B$301,$A53,'Detailed Results'!$Q$2:$Q$301,"Y")
A54: Cosmetics — 21 CFR 700-740 / MoCRA | B54: =COUNTIF('Detailed Results'!$B$2:$B$301,$A54) | C54: =COUNTIFS('Detailed Results'!$B$2:$B$301,$A54,'Detailed Results'!$L$2:$L$301,"OK") | D54: =COUNTIFS('Detailed Results'!$B$2:$B$301,$A54,'Detailed Results'!$M$2:$M$301,"PASS") | E54: =COUNTIFS('Detailed Results'!$B$2:$B$301,$A54,'Detailed Results'!$M$2:$M$301,"FAIL") | F54: =COUNTIFS('Detailed Results'!$B$2:$B$301,$A54,'Detailed Results'!$M$2:$M$301,"ERROR") | G54: =COUNTIFS('Detailed Results'!$B$2:$B$301,$A54,'Detailed Results'!$M$2:$M$301,"REQUIRES SME REVIEW") | H54: =COUNTIFS('Detailed Results'!$B$2:$B$301,$A54,'Detailed Results'!$Q$2:$Q$301,"Y")
A55: Biologics — 21 CFR 600-680 | B55: =COUNTIF('Detailed Results'!$B$2:$B$301,$A55) | C55: =COUNTIFS('Detailed Results'!$B$2:$B$301,$A55,'Detailed Results'!$L$2:$L$301,"OK") | D55: =COUNTIFS('Detailed Results'!$B$2:$B$301,$A55,'Detailed Results'!$M$2:$M$301,"PASS") | E55: =COUNTIFS('Detailed Results'!$B$2:$B$301,$A55,'Detailed Results'!$M$2:$M$301,"FAIL") | F55: =COUNTIFS('Detailed Results'!$B$2:$B$301,$A55,'Detailed Results'!$M$2:$M$301,"ERROR") | G55: =COUNTIFS('Detailed Results'!$B$2:$B$301,$A55,'Detailed Results'!$M$2:$M$301,"REQUIRES SME REVIEW") | H55: =COUNTIFS('Detailed Results'!$B$2:$B$301,$A55,'Detailed Results'!$Q$2:$Q$301,"Y")
... A66: SCOPE DISCIPLINE — Boundary Test | B66: =COUNTIF('Detailed Results'!$B$2:$B$301,$A66) | C66: =COUNTIFS('Detailed Results'!$B$2:$B$301,$A66,'Detailed Results'!$L$2:$L$301,"OK") | D66: =COUNTIFS('Detailed Results'!$B$2:$B$301,$A66,'Detailed Results'!$M$2:$M$301,"PASS") | E66: =COUNTIFS('Detailed Results'!$B$2:$B$301,$A66,'Detailed Results'!$M$2:$M$301,"FAIL") | F66: =COUNTIFS('Detailed Results'!$B$2:$B$301,$A66,'Detailed Results'!$M$2:$M$301,"ERROR") | G66: =COUNTIFS('Detailed Results'!$B$2:$B$301,$A66,'Detailed Results'!$M$2:$M$301,"REQUIRES SME REVIEW") | H66: =COUNTIFS('Detailed Results'!$B$2:$B$301,$A66,'Detailed Results'!$Q$2:$Q$301,"Y")

Sheet Detailed Results
A1: Question ID | B1: Category (Domain) | C1: Question Type | D1: Difficulty | E1: Question (verbatim, col F) | F1: Expected Answer / Reference (col J, DRAFT) | G1: Model Answer (as shown to user) | H1: Citation Expected (col G/H, DRAFT) | I1: Citation Provided | J1: Citation vs Draft Key (indicator) | K1: Response Time (s) | L1: Execution Status | M1: Result | N1: Error | O1: Scoring Notes | P1: Evaluator Notes (verification + machine checks) | Q1: Borderline - SME second look | R1: L Citation Exact (1/0) | S1: M Fabricated Citation (1=fail) | T1: N Substantive (0-2) | U1: O Completeness (0-2) | V1: P Scope Discipline (1/0) | W1: Q ISO Clause (1/0/blank) | X1: Answerability State | Y1: Final Validation | Z1: Repair Applied | AA1: Evidence Retrieved | AB1: ISO Clauses Named | AC1: Raw Model Output (before validation/repair) | AD1: Key Verified (col K) | AE1: Benchmark Row
A2: S-001 | B2: Dietary Supplements — 21 CFR 111 | C2: Direct Lookup | D2: Basic | E2: Who is subject to the dietary supplement CGMP requirements of 21 CFR Part 111? | F2: [DRAFT KEY - NOT SME-VERIFIED] Manufacture, package, label, or hold a dietary supplement; includes those who hold for distribution; excludes certain retailers/holders as specified. | G2: The generated answer could not be validated against the retrieved regulatory evidence, so it is not shown. The retrieved sources were not verified to answer the question as asked, so their text is not quoted as an answer. Sources consulted: 21 CFR 111.103, 21 CFR 111.105, 21 CFR 111.10(a), 21 CFR 111.110, 21 CFR 111.113(a) and 16 more. | H2: 21 CFR 111.1 | I2: none (answer withheld) | J2: no CFR citation | K2: 28.15 | L2: OK | M2: FAIL | O2: No answer delivered: the pipeline withheld a degenerate, looping draft. 111.1 (who is subject) is never stated and nothing is cited. | P2: Draft key 111.1 verified correct against the snapshot. Raw output repeated quality-control sentences unrelated to the question. || MACHINE CHECKS: indicator: citation vs draft key: no CFR citation | indicator: answer withheld by validation (likely incomplete / no substantive answer) | pipeline validator codes on raw output: degenerate_output, truncated, low_overlap_with_cited_source, repeated_statement | Q2: N | R2: 0 | S2: 0 | T2: 0 | U2: 0 | V2: 1 | X2: ANSWERABLE | Y2: unsupported | Z2: unvalidated_answer_withheld | AA2: 21 CFR 111.103; 21 CFR 111.105; 21 CFR 111.10(a); 21 CFR 111.110; 21 CFR 111.113(a); 21 CFR 111.117; 21 CFR 111.120; 21 CFR 111.123(a); 21 CFR 111.127; 21 CFR 111.12(a); 21 CFR 111.130; 21 CFR 111.135; 21 CFR 111.13(a); 21 CFR 111.140(a); 21 CFR 111.14(a); 21 CFR 111.153; 21 CFR 111.155(a); 21 CFR 111.15(a); 21 CFR 111.160(a); 21 CFR 111.165(a); 21 CFR 111.16 | AC2: Who is subject to the dietary supplement CGMP requirements of 21 CFR Part 111? [1] Quality control personnel must ensure that your manufacturing, packaging, labeling, and holding operations ensure the quality of the dietary supplement and that the dietary supplement is packaged and labeled as specified in the master manufacturing record. [1] Quality control personnel must conduct a material review and make a disposition decision if [1] Quality control personnel must ensure that your manufacturing, packaging, labeling, and holding operations ensure the quality of the dietary supplement and that the dietary supplement is packaged and labeled as specified in the master manufacturing record. [1] Quality control personnel must ensure that your manufacturing, packaging, labeling, and holding operations ensure the quality of the dietary supplement and that the dietary supplement is packaged and labeled as specified in the master manufacturing record. [1] Quality control personnel must ensure that your manufacturing, packaging, labeling, and holding operations ensure the quality of the dietary supplement and that the dietary supplement is packaged and labeled as specified in the master manufacturing record. [1] Quality control personnel must ensure that your manufacturing, packaging, | AD2: unmarked | AE2: 2
A3: S-002 | B3: Dietary Supplements — 21 CFR 111 | C3: Direct Lookup | D3: Basic | E3: Where are the definitions that apply to 21 CFR Part 111 located, and does Part 111 incorporate definitions from elsewhere? | F3: [DRAFT KEY - NOT SME-VERIFIED] Definitions section for Part 111; also incorporates FD&C Act and Part 1 definitions by reference. | G3: 21 CFR Part 111 requires written procedures for quality control operations, including material review and disposition decisions, equipment, instruments, and controls, components, packaging, and labels, master manufacturing records, batch production records, and packaging and labeling operations, personnel qualification requirements, and returned dietary supplements. The requirements under this subpart include: - Written procedures for quality control operations, as outlined in 21 CFR 111.103, 111.105, 111.10(a), 111.110, 111.113(a), 111.117, 111.120, 111.123(a), 111.127, 111.12(a), 111.130, 111.135, 111.13(a), and 111.140(a). - Personnel qualification requirements, as outlined in 21 CFR 111.140(a) and 111.14(a). - Records required under this subpart, including master manufacturing records, batch production records, and packaging and labeling operations, as outlined in 21 CFR 111.14(a). - Requirements for components, packaging, and labels before use, as outlined in 21 CFR 111.127. - Requirements for returned dietary supplements, as outlined in 21 CFR 111.135. - Requirements for product complaints, as outlined in 21 CFR 111.13(a). - Requirements for supervision of quality control operations, as outlined in 21 CFR 111.130. - Requirements for sanitation and ground maintenance, as outlined in 21 CFR 111.15(a). - Requirements for packaging and labels received, as outlined in 21 CFR 111.160(a). - Requirements for contamination and deterioration checks, as outlined in 21 CFR 111.17. 21 CFR 111.103 (eCFR, binding, verbatim): You must establish and follow written procedures for the responsibilities of the quality control operations, including written procedures for conducting a material review and making a disposition decision, and for approving or rejecting any reprocessing [1]. 21 CFR 111.135 (eCFR, binding, verbatim): Quality control operations for product complaints must include reviewing and approving decisions about whether to investigate a product complaint and reviewing and approving the findings and followup action of any investigation performed [12]. 21 CFR 111.153 (eCFR, binding, verbatim): You must establish and follow written procedures for fulfilling the requirements of this subpart G [16]. 21 CFR 111.155(a) (eCFR, binding, verbatim): (a) You must visually examine each immediate container or grouping of immediate containers in a shipment that you receive for appropriate content label, container damage, or broken seals to determine whether the container condition may have resulted in contamination or deterioration of the components; [17]. 21 CFR 111.165(a) (eCFR, binding, verbatim): (a) You must visually examine each immediate container or grouping of immediate containers in a shipment of product that you receive for packaging or labeling as a dietary supplement (and for distribution rather than for return to the supplier) for appropriate content label, container damage, or broken seals to determine whether the container condition may have resulted in contamination or deterioration of the received product [20]. 21 CFR 111.16 (eCFR, binding, verbatim): You must establish and follow written procedures for cleaning the physical plant and for pest control [21]. | H3: 21 CFR 111.3 | I3: 21 CFR Part 111, 21 CFR 111.103, 111.105, 111.10(a), 111.110, 111.113(a), 111.117, 111.120, 111.123(a), 111.127, 111.12(a), 111.130, 111.135, 111.13(a), 111.140(a), 111.14(a), 21 CFR 111.15(a), 21 CFR 111.160(a), 21 CFR 111.17, 21 CFR 111.153, 21 CFR 111.155(a), 21 CFR 111.165(a), 21 CFR 111.16 | J3: same part, different section | K3: 54.49 | L3: OK | M3: FAIL | O3: Does not answer the question: lists written-procedure requirements instead of identifying 111.3 and the incorporated FD&C Act section 201 / Part 1 definitions. Cites 21 CFR 111.17, which does not exist (fabricated citation, rubric M=1). | P3: Draft key 111.3 verified correct. Cited sections (111.103, 111.135, 111.153, 111.155, 111.165, 111.16) are all unrelated to definitions. || MACHINE CHECKS: indicator: citation vs draft key: same part, different section | indicator: cited provision has no entry in the current snapshot (removed/superseded or non-existent): 21 CFR 111.17 (section_not_in_db) | pipeline validator codes on raw output: uncited_statement, material_group_uncovered | Q3: N | R3: 0 | S3: 1 | T3: 0 | U3: 0 | V3: 1 | X3: ANSWERABLE | Y3: valid | Z3: appended_missing_items | AA3: 21 CFR 111.103; 21 CFR 111.105; 21 CFR 111.10(a); 21 CFR 111.110; 21 CFR 111.113(a); 21 CFR 111.117; 21 CFR 111.120; 21 CFR 111.123(a); 21 CFR 111.127; 21 CFR 111.12(a); 21 CFR 111.130; 21 CFR 111.135; 21 CFR 111.13(a); 21 CFR 111.140(a); 21 CFR 111.14(a); 21 CFR 111.153; 21 CFR 111.155(a); 21 CFR 111.15(a); 21 CFR 111.160(a); 21 CFR 111.165(a); 21 CFR 111.16 | AC3: 21 CFR Part 111 requires written procedures for quality control operations, including material review and disposition decisions, equipment, instruments, and controls, components, packaging, and labels, master manufacturing records, batch production records, and packaging and labeling operations, personnel qualification requirements, and returned dietary supplements. The requirements under this subpart include: - Written procedures for quality control operations, as outlined in 21 CFR 111.103, 111.105, 111.10(a), 111.110, 111.113(a), 111.117, 111.120, 111.123(a), 111.127, 111.12(a), 111.130, 111.135, 111.13(a), and 111.140(a). - Personnel qualification requirements, as outlined in 21 CFR 111.140(a) and 111.14(a). - Records required under this subpart, including master manufacturing records, batch production records, and packaging and labeling operations, as outlined in 21 CFR 111.14(a). - Requirements for components, packaging, and labels before use, as outlined in 21 CFR 111.127. - Requirements for returned dietary supplements, as outlined in 21 CFR 111.135. - Requirements for product complaints, as outlined in 21 CFR 111.13(a). - Requirements for supervision of quality control operations, as outlined in 21 CFR 111.130. - Requirements for sanitation and ground maintenance, as outlined in 21 CFR 111.15(a). - Requirements for packaging and labels received, as outlined in 21 CFR 111.160(a). - Requirements for contamination and deterioration checks, as outlined in 21 CFR 111.17. | AD3: unmarked | AE3: 3
A4: S-003 | B4: Dietary Supplements — 21 CFR 111 | C4: Direct Lookup | D4: Basic | E4: What personnel qualification requirements apply under the Part 111 personnel subpart? | F4: [DRAFT KEY - NOT SME-VERIFIED] Qualified persons, education/training/experience, supervisor requirements. | G4: Under the Part 111 personnel subpart, personnel qualification requirements apply. You must have qualified employees who manufacture, package, label, or hold dietary supplements. [1] | H4: 21 CFR 111.12 | I4: Part 111, 21 CFR 111.103 | J4: same part, different section | K4: 6.75 | L4: OK | M4: FAIL | O4: States 111.12(a) correctly (qualified employees) but attributes it to source [1] = 111.103, the wrong section, and omits 111.12(b) quality-control separation of duties and (c) education/training/experience. | P4: Draft key 111.12 verified correct. Substance partly right, citation wrong and answer materially incomplete. || MACHINE CHECKS: indicator: citation vs draft key: same part, different section | pipeline validator codes on raw output: low_overlap_with_cited_source | Q4: N | R4: 0 | S4: 0 | T4: 1 | U4: 0 | V4: 1 | X4: ANSWERABLE | Y4: valid | AA4: 21 CFR 111.103; 21 CFR 111.105; 21 CFR 111.10(a); 21 CFR 111.110; 21 CFR 111.113(a); 21 CFR 111.117; 21 CFR 111.120; 21 CFR 111.123(a); 21 CFR 111.127; 21 CFR 111.12(a); 21 CFR 111.130; 21 CFR 111.135; 21 CFR 111.13(a); 21 CFR 111.140(a); 21 CFR 111.14(a); 21 CFR 111.153; 21 CFR 111.155(a); 21 CFR 111.15(a); 21 CFR 111.160(a); 21 CFR 111.165(a); 21 CFR 111.16 | AC4: Under the Part 111 personnel subpart, personnel qualification requirements apply. You must have qualified employees who manufacture, package, label, or hold dietary supplements. [1] | AD4: unmarked | AE4: 4
A5: S-004 | B5: Dietary Supplements — 21 CFR 111 | C5: Direct Lookup | D5: Basic | E5: What hygienic practices must employees follow under Part 111? | F5: [DRAFT KEY - NOT SME-VERIFIED] Handwashing, outer garments, jewelry, eating/drinking restrictions, disease control. | G5: Under Part 111, employees must establish and follow written procedures for conducting a material review and making a disposition decision, and for approving or rejecting any reprocessing. [1] Under Part 111, quality control personnel must ensure that your manufacturing, packaging, labeling, and holding operations ensure the quality of the dietary supplement and that the dietary supplement is packaged and labeled as specified in the master manufacturing record. To do so, quality control personnel must perform operations that include: [1] Under Part 111, preventing microbial contamination from sick or infected personnel and for hygienic practices must include measures to exclude any person who might be a source of microbial contamination, due to a health condition, of any material, including components, dietary supplements, and contact surfaces used in the manufacture, packaging, labeling, or holding of a dietary supplement. [3] Under Part 111, quality control operations for laboratory operations associated with the production and process control system must include: [1] Under Part 111, quality control operations for components, packaging, and labels before use in the manufacture of a dietary supplement must include: [1] Under Part 111, quality control operations for the master manufacturing record, the batch production record, and manufacturing operations must include: [1] Under Part 111, quality control operations for packaging and labeling operations must include: [1] Under Part 111, qualified employees must be assigned to supervise the manufacturing, packaging, labeling, or holding of dietary supplements. [13] Under Part 111, records required under this subpart F must be made and kept in accordance with subpart P of this part. [14] Under Part 111, records required under this subpart B must be made and kept in accordance with subpart P of this part. [15] Under Part 111, written procedures must be established and followed for fulfilling the requirements of this subpart G. [16] Under Part 111, visual examination of immediate containers or grouping of immediate containers in a shipment for appropriate content label, container damage, or broken seals must be conducted to determine whether the container condition may have resulted in contamination or deterioration of the components. [17] Under Part 111, grounds must be kept in a condition that protects against contamination of components, dietary supplements, or contact surfaces. [18] Under Part 111, packaging and labels received for packaging or labeling as a dietary supplement must be visually examined for appropriate content label, container damage, or broken seals to determine whether the container condition may have resulted in contamination or deterioration of the received product. [19] Under Part 111, the requirements for a product received for packaging or labeling as a dietary supplement (and for distribution rather than for return to the supplier) must include visual examination of immediate containers or grouping of immediate containers. [20] | H5: 21 CFR 111.13 | I5: Part 111, 21 CFR 111.103, 21 CFR 111.10(a), 21 CFR 111.13(a), 21 CFR 111.140(a), 21 CFR 111.14(a), 21 CFR 111.153, 21 CFR 111.155(a), 21 CFR 111.15(a), 21 CFR 111.160(a), 21 CFR 111.165(a) | J5: draft section cited | K5: 68.87 | L5: OK | M5: FAIL | O5: Mostly recites unrelated quality-control procedure text. One sentence on excluding sick personnel (cited to 111.10(a)) is correct, but handwashing, outer garments, jewellery and eating/drinking restrictions are all missing; the first statement cites 111.103 for a hygiene question. | P5: DRAFT KEY APPEARS INCORRECT: it names 111.13, which is supervisor requirements; hygienic practices are in 111.10. The model is not penalised for the key mismatch - it fails on substance and completeness. || MACHINE CHECKS: pipeline validator codes on raw output: uncited_statement, low_overlap_with_cited_source, repeated_statement | Q5: N | R5: 0 | S5: 0 | T5: 1 | U5: 0 | V5: 1 | X5: ANSWERABLE | Y5: valid | AA5: 21 CFR 111.103; 21 CFR 111.105; 21 CFR 111.10(a); 21 CFR 111.110; 21 CFR 111.113(a); 21 CFR 111.117; 21 CFR 111.120; 21 CFR 111.123(a); 21 CFR 111.127; 21 CFR 111.12(a); 21 CFR 111.130; 21 CFR 111.135; 21 CFR 111.13(a); 21 CFR 111.140(a); 21 CFR 111.14(a); 21 CFR 111.153; 21 CFR 111.155(a); 21 CFR 111.15(a); 21 CFR 111.160(a); 21 CFR 111.165(a); 21 CFR 111.16 | AC5: Under Part 111, employees must establish and follow written procedures for conducting a material review and making a disposition decision, and for approving or rejecting any reprocessing. [1] Under Part 111, quality control personnel must ensure that your manufacturing, packaging, labeling, and holding operations ensure the quality of the dietary supplement and that the dietary supplement is packaged and labeled as specified in the master manufacturing record. To do so, quality control personnel must perform operations that include: [1] Under Part 111, preventing microbial contamination from sick or infected personnel and for hygienic practices must include measures to exclude any person who might be a source of microbial contamination, due to a health condition, of any material, including components, dietary supplements, and contact surfaces used in the manufacture, packaging, labeling, or holding of a dietary supplement. [3] Under Part 111, quality control operations for laboratory operations associated with the production and process control system must include: [1] Under Part 111, quality control operations for components, packaging, and labels before use in the manufacture of a dietary supplement must include: [1] Under Part 111, quality control operations for the master manufacturing record, the batch production record, and manufacturing operations must include: [1] Under Part 111, quality control operations for packaging and labeling operations must include: [1] Under Part 111, qualified employees must be assigned to supervise the manufacturing, packaging, labeling, or holding of dietary supplements. [13] Under Part 111, records required under this subpart F must be made and kept in accordance with subpart P of this part. [14] Under Part 111, records required under this subpart B must be made and kept in accordance with subpart P of this part. [15] Under Part 111, written procedures must be established and followed for fulfilling the requirements of this subpart G. [16] Under Part 111, visual examination of immediate containers or grouping of immediate containers in a shipment for appropriate content label, container damage, or broken seals must be conducted to determine whether the container condition may have resulted in contamination or deterioration of the components. [17] Under Part 111, grounds must be kept in a condition that protects against contamination of components, dietary supplements, or contact surfaces. [18] Under Part 111, packaging and labels received for packaging or labeling as a dietary supplement must be visually examined for appropriate content label, container damage, or broken seals to determine whether the container condition may have resulted in contamination or deterioration of the received product. [19] Under Part 111, the requirements for a product received for packaging or labeling as a dietary supplement (and for distribution rather than for return to the supplier) must include visual examination of immediate containers or grouping of immediate containers. [20] | AD5: unmarked | AE5: 5
A6: S-005 | B6: Dietary Supplements — 21 CFR 111 | C6: Cross-Reference | D6: Intermediate | E6: What records must be made and kept under the Part 111 personnel subpart, and where are the general recordkeeping requirements for those records found? | F6: [DRAFT KEY - NOT SME-VERIFIED] Subpart B records requirement plus Subpart P general records/retention rules. | G6: Under Part 111 personnel subpart, records must be made and kept for quality control operations, including written procedures for conducting a material review and making a disposition decision, approving or rejecting any reprocessing, preventing microbial contamination from sick or infected personnel, hygienic practices, laboratory operations, and process control systems, and for components, packaging, and labels before use in the manufacture of a dietary supplement. These records must be kept in accordance with subpart P of this part [14]. | H6: 21 CFR 111.14; cross-ref 21 CFR 111.605 and 111.610 | I6: Part 111, 21 CFR 111.140(a) | J6: same part, different section | K6: 12.93 | L6: OK | M6: FAIL | O6: The subpart P cross-reference is right in substance but cited to [14] = 111.140(a) instead of 111.14/111.605. The required records (written procedures for subpart B, training documentation) are replaced by unrelated quality-control content. | P6: Draft key 111.14 + 111.605/111.610 verified correct against the snapshot. || MACHINE CHECKS: indicator: citation vs draft key: same part, different section | pipeline validator codes on raw output: uncited_statement | Q6: N | R6: 0 | S6: 0 | T6: 1 | U6: 0 | V6: 1 | X6: ANSWERABLE | Y6: valid | AA6: 21 CFR 111.103; 21 CFR 111.105; 21 CFR 111.10(a); 21 CFR 111.110; 21 CFR 111.113(a); 21 CFR 111.117; 21 CFR 111.120; 21 CFR 111.123(a); 21 CFR 111.127; 21 CFR 111.12(a); 21 CFR 111.130; 21 CFR 111.135; 21 CFR 111.13(a); 21 CFR 111.140(a); 21 CFR 111.14(a); 21 CFR 111.153; 21 CFR 111.155(a); 21 CFR 111.15(a); 21 CFR 111.160(a); 21 CFR 111.165(a); 21 CFR 111.16 | AC6: Under Part 111 personnel subpart, records must be made and kept for quality control operations, including written procedures for conducting a material review and making a disposition decision, approving or rejecting any reprocessing, preventing microbial contamination from sick or infected personnel, hygienic practices, laboratory operations, and process control systems, and for components, packaging, and labels before use in the manufacture of a dietary supplement. These records must be kept in accordance with subpart P of this part [14]. | AD6: unmarked | AE6: 6
A7: S-006 | B7: Dietary Supplements — 21 CFR 111 | C7: Direct Lookup | D7: Basic | E7: What sanitation requirements apply to the physical plant and grounds under Part 111? | F7: [DRAFT KEY - NOT SME-VERIFIED] Litter/waste, pest control, cleaning, sanitizing agents, toilet facilities, plumbing. | G7: Under Part 111, sanitation requirements apply to the physical plant and grounds, ensuring that the grounds protect against contamination of components, dietary supplements, or contact surfaces. [18] | H7: 21 CFR 111.15 | I7: Part 111, 21 CFR 111.15(a) | J7: draft section cited | K7: 7.16 | L7: OK | M7: FAIL | O7: Correctly cited (111.15(a)) and not wrong, but gives only the general purpose of ground maintenance. Litter and waste, pest control, cleaning, sanitising agents, toilet facilities and plumbing - the substance of the section - are all omitted (material omission, rubric O=0). | P7: Draft key 111.15 verified correct. Citation accuracy satisfied; fails on completeness only. || MACHINE CHECKS: no machine indicators | Q7: N | R7: 1 | S7: 0 | T7: 1 | U7: 0 | V7: 1 | X7: ANSWERABLE | Y7: valid | AA7: 21 CFR 111.103; 21 CFR 111.105; 21 CFR 111.10(a); 21 CFR 111.110; 21 CFR 111.113(a); 21 CFR 111.117; 21 CFR 111.120; 21 CFR 111.123(a); 21 CFR 111.127; 21 CFR 111.12(a); 21 CFR 111.130; 21 CFR 111.135; 21 CFR 111.13(a); 21 CFR 111.140(a); 21 CFR 111.14(a); 21 CFR 111.153; 21 CFR 111.155(a); 21 CFR 111.15(a); 21 CFR 111.160(a); 21 CFR 111.165(a); 21 CFR 111.16 | AC7: Under Part 111, sanitation requirements apply to the physical plant and grounds, ensuring that the grounds protect against contamination of components, dietary supplements, or contact surfaces. [18] | AD7: unmarked | AE7: 7
A8: S-007 | B8: Dietary Supplements — 21 CFR 111 | C8: Direct Lookup | D8: Intermediate | E8: What are the water supply requirements for a dietary supplement facility? | F8: [DRAFT KEY - NOT SME-VERIFIED] Water that contacts components/product or contact surfaces must be safe and sanitary quality. | G8: The water supply requirements for a dietary supplement facility are outlined in the FDA Guidance: Guidance for Industry: Questions and Answers Regarding Adverse Event Reporting and Recordkeeping for Dietary Supplements. A dietary supplement must be labeled as such and intended for ingestion. It must not be represented for use as a conventional food or as a sole item of a meal or the diet. Additionally, the facility must clearly identify, hold, and control under a quarantine system for appropriate disposition any dietary supplement that is rejected and unsuitable for use in manufacturing, packaging, or labeling operations. The requirements apply to devices and persons that are subject to the quarantine system [1] [4]. | H8: 21 CFR 111.16 | I8: 21 CFR 111.470 | J8: same part, different section | K8: 17.64 | L8: OK | M8: FAIL | O8: Answers with adverse-event reporting guidance and quarantine/labelling text that has nothing to do with water supply. No water requirement is stated. | P8: DRAFT KEY APPEARS INCORRECT: 111.16 is written procedures for cleaning and pest control; water supply requirements sit in 111.15. The answer is wrong against either reading. || MACHINE CHECKS: indicator: citation vs draft key: same part, different section | pipeline validator codes on raw output: invented_condition | Q8: N | R8: 0 | S8: 0 | T8: 0 | U8: 0 | V8: 1 | X8: UNKNOWN | Y8: valid | Z8: invented_conditions_removed | AA8: FDA Guidance: Guidance for Industry: Questions and Answers Regarding Adverse Event Reporting and Recordkeeping for Dietary Supplements as Required by the Dietary Supplement and Nonprescription Drug Consumer Protection Act (final, 2013-09-01, Docket FDA-2007-D-0372); 21 CFR 111.370; 21 CFR 111.155(a); 21 CFR 111.470; FDA Guidance: Guidance for Industry: Distinguishing Liquid Dietary Supplements from Beverages (final, 2014-01-14, Docket FDA-2009-D-0542) | AC8: The water supply requirements for a dietary supplement facility are outlined in the FDA Guidance: Guidance for Industry: Questions and Answers Regarding Adverse Event Reporting and Recordkeeping for Dietary Supplements. A dietary supplement must be labeled as such and intended for ingestion. It must not be represented for use as a conventional food or as a sole item of a meal or the diet. Additionally, the facility must clearly identify, hold, and control under a quarantine system for appropriate disposition any dietary supplement that is rejected and unsuitable for use in manufacturing, packaging, or labeling operations. If applicable, the requirements also apply to components of dietary supplements and to distributing dietary supplements. The requirements apply to devices and persons that are subject to the quarantine system. [1] [4] | AD8: unmarked | AE8: 8
A9: S-008 | B9: Dietary Supplements — 21 CFR 111 | C9: Direct Lookup | D9: Intermediate | E9: What design and construction requirements apply to the physical plant under Part 111? | F9: [DRAFT KEY - NOT SME-VERIFIED] Suitable size/construction/design, separation of operations, lighting, ventilation, floors/walls/ceilings. | G9: Under Part 111, the design and construction requirements apply to the physical plant and grounds, including visual examination of containers for appropriate content labels, container damage, or broken seals to determine if contamination or deterioration may have occurred. [1] The requirements for quality control personnel include ensuring the quality of dietary supplements through written procedures, including material reviews and disposition decisions, and for preventing microbial contamination from sick or infected personnel. [1] The requirements for preventing microbial contamination include excluding sources of microbial contamination from operations, and for hygienic practices. [1] The requirements for quality control operations related to laboratory operations include conducting material reviews and disposition decisions. [1] The requirements for quality control operations related to equipment, instruments, and controls include ensuring proper operation of these systems. [1] The requirements for quality control operations related to components, packaging, and labels before use include ensuring proper packaging and labeling. [1] The requirements for quality control operations related to the master manufacturing record, batch production record, and manufacturing operations include maintaining these records. [1] The requirements for quality control operations related to packaging and labeling operations include ensuring proper packaging and labeling. [1] The requirements for personnel qualification include having qualified employees who handle dietary supplements. [1] The requirements for supervisor requirements include assigning qualified personnel to supervise operations. [1] The requirements for records include making and keeping records required under this subpart F in accordance with subpart P of this part. [1] | H9: 21 CFR 111.20 | I9: Part 111, 21 CFR 111.103 | J9: same part, different section | K9: 49.03 | L9: OK | M9: FAIL | O9: Describes container inspection and quality-control operations instead of plant design and construction. None of 111.20's requirements (size, space, separation of operations, lighting, ventilation) appear; cited to 111.103. | P9: Draft key 111.20 verified correct against the snapshot. || MACHINE CHECKS: indicator: citation vs draft key: same part, different section | pipeline validator codes on raw output: low_overlap_with_cited_source | Q9: N | R9: 0 | S9: 0 | T9: 0 | U9: 0 | V9: 1 | X9: ANSWERABLE | Y9: valid | AA9: 21 CFR 111.103; 21 CFR 111.105; 21 CFR 111.10(a); 21 CFR 111.110; 21 CFR 111.113(a); 21 CFR 111.117; 21 CFR 111.120; 21 CFR 111.123(a); 21 CFR 111.127; 21 CFR 111.12(a); 21 CFR 111.130; 21 CFR 111.135; 21 CFR 111.13(a); 21 CFR 111.140(a); 21 CFR 111.14(a); 21 CFR 111.153; 21 CFR 111.155(a); 21 CFR 111.15(a); 21 CFR 111.160(a); 21 CFR 111.165(a); 21 CFR 111.16 | AC9: Under Part 111, the design and construction requirements apply to the physical plant and grounds, including visual examination of containers for appropriate content labels, container damage, or broken seals to determine if contamination or deterioration may have occurred. [1] The requirements for quality control personnel include ensuring the quality of dietary supplements through written procedures, including material reviews and disposition decisions, and for preventing microbial contamination from sick or infected personnel. [1] The requirements for preventing microbial contamination include excluding sources of microbial contamination from operations, and for hygienic practices. [1] The requirements for quality control operations related to laboratory operations include conducting material reviews and disposition decisions. [1] The requirements for quality control operations related to equipment, instruments, and controls include ensuring proper operation of these systems. [1] The requirements for quality control operations related to components, packaging, and labels before use include ensuring proper packaging and labeling. [1] The requirements for quality control operations related to the master manufacturing record, batch production record, and manufacturing operations include maintaining these records. [1] The requirements for quality control operations related to packaging and labeling operations include ensuring proper packaging and labeling. [1] The requirements for personnel qualification include having qualified employees who handle dietary supplements. [1] The requirements for supervisor requirements include assigning qualified personnel to supervise operations. [1] The requirements for records include making and keeping records required under this subpart F in accordance with subpart P of this part. [1] | AD9: unmarked | AE9: 9
A10: S-009 | B10: Dietary Supplements — 21 CFR 111 | C10: Direct Lookup | D10: Intermediate | E10: What requirements apply to automated, mechanical, or electronic equipment used in dietary supplement manufacturing? | F10: [DRAFT KEY - NOT SME-VERIFIED] Design/installation for intended use, calibration, backup, controls to prevent unauthorized changes. | G10: The requirements apply to automated, mechanical, or electronic equipment used in dietary supplement manufacturing. These include: - Design or select equipment to ensure that dietary supplement specifications are consistently met [1]. - Determine the suitability of the equipment by ensuring that your equipment is capable of operating satisfactorily within the operating limits required by the process [2]. - Establish and use appropriate controls to ensure that the equipment functions in accordance with its intended use. These controls must be approved by quality control personnel [4]. - Routinely calibrate, inspect, or check the equipment to ensure proper performance. Your quality control personnel must periodically review these calibrations, inspections, or checks [5]. - Establish and use appropriate controls for automated, mechanical, and electronic equipment (including software for a computer controlled process) to ensure that any changes to the manufacturing, packaging, labeling, holding, or other operations are approved by quality control personnel and instituted only by authorized personnel [6]. - Equipment used in automated, mechanical, or electronic systems must be identified and described [7]. | H10: 21 CFR 111.30 | I10: 21 CFR 111.30, 21 CFR 111.30(a), 21 CFR 111.30(e), 21 CFR 111.30(c), 21 CFR 111.30(d), 21 CFR 111.27(a)(1)(v) | J10: draft section cited | K10: 17.98 | L10: OK | M10: FAIL | O10: Substantively correct and complete for 111.30(a)-(e), but two citation errors: the suitability requirement (111.30(b)) is cited as 111.30(a), and a closing requirement that equipment 'must be identified and described' is attributed to 111.27(a)(1)(v), which does not state it. | P10: Draft key 111.30 verified correct. Best answer in this block; fails only on citation accuracy, which gate G1 scores at 99%. || MACHINE CHECKS: no machine indicators | Q10: N | R10: 0 | S10: 0 | T10: 2 | U10: 2 | V10: 1 | X10: UNKNOWN | Y10: valid | AA10: 21 CFR 111.30; 21 CFR 111.30(a); 21 CFR 111.30(b); 21 CFR 111.30(e); 21 CFR 111.30(c); 21 CFR 111.30(d); 21 CFR 111.27(a)(1)(v); FDA Guidance: BLA for Minimally Manipulated, Unrelated Allogeneic Placental/Umbilical Cord Blood Intended for Hematopoietic and Immunologic Reconstitution in Patients with Disorders Affecting the Hematopoietic System: Guidance for Industry (final, 2014-03-01, Docket FDA-2006-D-0157) | AC10: The requirements apply to automated, mechanical, or electronic equipment used in dietary supplement manufacturing. These include: - Design or select equipment to ensure that dietary supplement specifications are consistently met [1]. - Determine the suitability of the equipment by ensuring that your equipment is capable of operating satisfactorily within the operating limits required by the process [2]. - Establish and use appropriate controls to ensure that the equipment functions in accordance with its intended use. These controls must be approved by quality control personnel [4]. - Routinely calibrate, inspect, or check the equipment to ensure proper performance. Your quality control personnel must periodically review these calibrations, inspections, or checks [5]. - Establish and use appropriate controls for automated, mechanical, and electronic equipment (including software for a computer controlled process) to ensure that any changes to the manufacturing, packaging, labeling, holding, or other operations are approved by quality control personnel and instituted only by authorized personnel [6]. - Equipment used in automated, mechanical, or electronic systems must be identified and described [7]. | AD10: unmarked | AE10: 10
A11: S-010 | B11: Dietary Supplements — 21 CFR 111 | C11: Direct Lookup | D11: Basic | E11: What is the requirement to establish a production and process control system under Part 111? | F11: [DRAFT KEY - NOT SME-VERIFIED] Establish and follow written procedures covering all stages of manufacturing, packaging, labeling, holding. | G11: Under Part 111, you must establish and follow written procedures for the responsibilities of the quality control operations, including written procedures for conducting a material review and making a disposition decision, and for approving or rejecting any reprocessing. [1] Under Part 111, quality control personnel must ensure that your manufacturing, packaging, labeling, and holding operations ensure the quality of the dietary supplement and that the dietary supplement is packaged and labeled as specified in the master manufacturing record. To do so, quality control personnel must perform operations that include: [1] Under Part 111, you must take measures to exclude from any operations any person who might be a source of microbial contamination, due to a health condition, of any material, including components, dietary supplements, and contact surfaces used in the manufacture, packaging, labeling, or holding of a dietary supplement. [3] Under Part 111, quality control operations for laboratory operations associated with the production and process control system must include: [4] Under Part 111, quality control operations for components, packaging, and labels before use in the manufacture of a dietary supplement must include: [7] Under Part 111, quality control operations for packaging and labeling operations must include: [9] Under Part 111, quality control personnel must conduct a material review and make a disposition decision if: [5] Under Part 111, quality control personnel must establish and follow written procedures for fulfilling the requirements of this subpart G. [16] Under Part 111, you must establish and follow written procedures for cleaning the physical plant and for pest control. [16] | H11: 21 CFR 111.55 | I11: Part 111, 21 CFR 111.103, 21 CFR 111.10(a), 21 CFR 111.110, 21 CFR 111.113(a), 21 CFR 111.120, 21 CFR 111.127, 21 CFR 111.153 | J11: same part, different section | K11: 64.17 | L11: OK | M11: FAIL | O11: Never states the 111.55 requirement to implement production and process controls covering all stages. Returns quality-control procedure text cited to 111.103, 111.110, 111.113(a), 111.120 and 111.127. | P11: Draft key 111.55 verified correct against the snapshot. || MACHINE CHECKS: indicator: citation vs draft key: same part, different section | pipeline validator codes on raw output: uncited_statement, low_overlap_with_cited_source | Q11: N | R11: 0 | S11: 0 | T11: 0 | U11: 0 | V11: 1 | X11: ANSWERABLE | Y11: valid | AA11: 21 CFR 111.103; 21 CFR 111.105; 21 CFR 111.10(a); 21 CFR 111.110; 21 CFR 111.113(a); 21 CFR 111.117; 21 CFR 111.120; 21 CFR 111.123(a); 21 CFR 111.127; 21 CFR 111.12(a); 21 CFR 111.130; 21 CFR 111.135; 21 CFR 111.13(a); 21 CFR 111.140(a); 21 CFR 111.14(a); 21 CFR 111.153; 21 CFR 111.155(a); 21 CFR 111.15(a); 21 CFR 111.160(a); 21 CFR 111.165(a); 21 CFR 111.16 | AC11: Under Part 111, you must establish and follow written procedures for the responsibilities of the quality control operations, including written procedures for conducting a material review and making a disposition decision, and for approving or rejecting any reprocessing. [1] Under Part 111, quality control personnel must ensure that your manufacturing, packaging, labeling, and holding operations ensure the quality of the dietary supplement and that the dietary supplement is packaged and labeled as specified in the master manufacturing record. To do so, quality control personnel must perform operations that include: [1] Under Part 111, you must take measures to exclude from any operations any person who might be a source of microbial contamination, due to a health condition, of any material, including components, dietary supplements, and contact surfaces used in the manufacture, packaging, labeling, or holding of a dietary supplement. [3] Under Part 111, quality control operations for laboratory operations associated with the production and process control system must include: [4] Under Part 111, quality control operations for components, packaging, and labels before use in the manufacture of a dietary supplement must include: [7] Under Part 111, quality control operations for packaging and labeling operations must include: [9] Under Part 111, quality control personnel must conduct a material review and make a disposition decision if: [5] Under Part 111, quality control personnel must conduct a material review and make a disposition decision if: [11] Under Part 111, quality control personnel must conduct a material review and make a disposition decision if: [12] Under Part 111, quality control personnel must conduct a material review and make a disposition decision if: [13] Under Part 111, quality control personnel must conduct a material review and make a disposition decision if: [14] Under Part 111, quality control personnel must conduct a material review and make a disposition decision if: [15] Under Part 111, quality control personnel must conduct a material review and make a disposition decision if: [16] Under Part 111, quality control personnel must establish and follow written procedures for fulfilling the requirements of this subpart G. [16] Under Part 111, you must establish and follow written procedures for cleaning the physical plant and for pest control. [16] | AD11: unmarked | AE11: 11
A12: S-011 | B12: Dietary Supplements — 21 CFR 111 | C12: Direct Lookup | D12: Intermediate | E12: What specifications must a dietary supplement manufacturer establish? | F12: [DRAFT KEY - NOT SME-VERIFIED] Component, in-process, packaging/label, finished batch, and product-received specifications. | G12: A dietary supplement manufacturer must establish product specifications for the identity, purity, strength, and composition of the finished batch, as well as limits on contamination that may adulterate or lead to adulteration. Additionally, they must establish component specifications for each component used in the manufacture, including identity and purity, strength, and composition. These specifications must also include limits on contamination that could result in adulteration. The requirements apply to the manufacturer and their customer [1] [4]. | H12: 21 CFR 111.70 | I12: 21 CFR 111.70(e) | J12: draft section cited | K12: 13.2 | L12: OK | M12: FAIL | O12: Product and component specifications are broadly right, but in-process (111.70(c)) and packaging/label (111.70(d)) specifications are omitted, component specifications are cited to the FSVP guidance rather than Part 111, and the closing scope statement ('applies to the manufacturer and their customer') is unsupported. | P12: Draft key 111.70 verified correct. Citing an FSVP import guidance as authority for a Part 111 requirement is a citation failure. || MACHINE CHECKS: pipeline validator codes on raw output: invented_condition | Q12: N | R12: 0 | S12: 0 | T12: 1 | U12: 0 | V12: 1 | X12: UNKNOWN | Y12: valid | Z12: invented_conditions_removed | AA12: 21 CFR 111.70(e); 21 CFR 111.70(b); FDA Guidance: Draft Guidance for Industry: New Dietary Ingredient Notifications and Related Issues (draft, 2024-04-03, Docket FDA-2011-D-0376); FDA Guidance: Guidance for Industry: Foreign Supplier Verification Programs for Importers of Food for Humans and Animals (final, 2023-01-10, Docket FDA-2017-D-5225) | AC12: A dietary supplement manufacturer must establish product specifications for the identity, purity, strength, and composition of the finished batch, as well as limits on contamination that may adulterate or lead to adulteration. Additionally, they must establish component specifications for each component used in the manufacture, including identity and purity, strength, and composition. These specifications must also include limits on contamination that could result in adulteration. If applicable, the manufacturer must also include specifications for the labels and packaging that may come into contact with dietary supplements, ensuring they are safe and suitable for their intended use. The requirements apply to the manufacturer and their customer. [1][4] | AD12: unmarked | AE12: 12
A13: S-012 | B13: Dietary Supplements — 21 CFR 111 | C13: Application | D13: Advanced | E13: A finished batch fails an identity specification. What does Part 111 require the firm to do, and who makes the disposition decision? | F13: [DRAFT KEY - NOT SME-VERIFIED] Determine whether specs are met, quality control personnel material review and disposition, treatment of deviations, reprocessing limits. | G13: Part 111 requires the firm to establish and follow written procedures for conducting a material review and making a disposition decision, and for approving or rejecting any reprocessing. The disposition decision is made by the quality control personnel. [1] | H13: 21 CFR 111.73; 111.75; 111.87; 111.90 | I13: Part 111, 21 CFR 111.103 | J13: same part, different section | K13: 9.1 | L13: OK | M13: FAIL | O13: Correctly says quality-control personnel make the disposition decision, but that proposition (111.87) is cited to 111.103, and the firm's obligations under 111.73, 111.75 and 111.90 (determine whether specifications are met, reprocessing limits) are absent. | P13: Draft key 111.73/111.75/111.87/111.90 verified correct. Half the question (what the firm must do) is unanswered. || MACHINE CHECKS: indicator: citation vs draft key: same part, different section | pipeline validator codes on raw output: uncited_statement | Q13: N | R13: 0 | S13: 0 | T13: 1 | U13: 0 | V13: 1 | X13: ANSWERABLE | Y13: valid | AA13: 21 CFR 111.103; 21 CFR 111.105; 21 CFR 111.10(a); 21 CFR 111.110; 21 CFR 111.113(a); 21 CFR 111.117; 21 CFR 111.120; 21 CFR 111.123(a); 21 CFR 111.127; 21 CFR 111.12(a); 21 CFR 111.130; 21 CFR 111.135; 21 CFR 111.13(a); 21 CFR 111.140(a); 21 CFR 111.14(a); 21 CFR 111.153; 21 CFR 111.155(a); 21 CFR 111.15(a); 21 CFR 111.160(a); 21 CFR 111.165(a); 21 CFR 111.16 | AC13: Part 111 requires the firm to establish and follow written procedures for conducting a material review and making a disposition decision, and for approving or rejecting any reprocessing. The disposition decision is made by the quality control personnel. [1] | AD13: unmarked | AE13: 13
A14: S-013 | B14: Dietary Supplements — 21 CFR 111 | C14: Direct Lookup | D14: Intermediate | E14: What representative samples must be collected under Part 111, and what reserve sample requirements apply? | F14: [DRAFT KEY - NOT SME-VERIFIED] Representative samples of components, packaging, labels, in-process, finished batch; reserve sample size, storage conditions, retention period. | G14: Under Part 111, the representative samples must be collected under 21 CFR 111.103 [1], which outlines the requirements for written procedures. Quality control personnel must ensure the quality of dietary supplements through written procedures, including conducting material reviews and making disposition decisions [2]. The quality control operations required for laboratory operations associated with the production and process control system must include material reviews and disposition decisions [4]. The quality control operations for equipment, instruments, and controls must include these activities [6]. The quality control operations for components, packaging, and labels before use in the manufacture of a dietary supplement must include these activities [7]. The quality control operations for the master manufacturing record, the batch production record, and manufacturing operations must include these activities [8]. The quality control operations for packaging and labeling operations must include these activities [9]. The records required under this subpart F must be made and kept in accordance with subpart P of this part [14]. The records required under this subpart B must be made and kept in accordance with subpart P of this part [15]. The written procedures for fulfilling the requirements of this subpart G must be established and followed [16]. The requirements under this subpart G apply to components of dietary supplements [17]. The sanitation requirements apply to the physical plant and grounds [18]. The requirements under this subpart G apply to packaging and labels received [19]. The requirements under this subpart G apply to a product received for packaging or labeling as a dietary supplement [20]. The requirements under this subpart C for written procedures include cleaning the physical plant and pest control [21]. 21 CFR 111.135 (eCFR, binding, verbatim): Quality control operations for product complaints must include reviewing and approving decisions about whether to investigate a product complaint and reviewing and approving the findings and followup action of any investigation performed [12]. | H14: 21 CFR 111.80; 111.83 | I14: Part 111, 21 CFR 111.103, 21 CFR 111.135, 21 CFR 111.105, 21 CFR 111.110, 21 CFR 111.117, 21 CFR 111.120, 21 CFR 111.123(a), 21 CFR 111.127, 21 CFR 111.140(a), 21 CFR 111.14(a), 21 CFR 111.153, 21 CFR 111.155(a), 21 CFR 111.15(a), 21 CFR 111.160(a), 21 CFR 111.165(a), 21 CFR 111.16 | J14: same part, different section | K14: 63.89 | L14: OK | M14: FAIL | O14: States that representative samples are collected 'under 21 CFR 111.103', which is wrong, and never reaches 111.80 or the 111.83 reserve-sample requirements (container-closure, batch identification, retention, twice-the-quantity). | P14: Draft key 111.80/111.83 verified correct against the snapshot. || MACHINE CHECKS: indicator: citation vs draft key: same part, different section | pipeline validator codes on raw output: provision_citation_mismatch, low_overlap_with_cited_source, material_group_uncovered, repeated_statement | Q14: N | R14: 0 | S14: 0 | T14: 0 | U14: 0 | V14: 1 | X14: ANSWERABLE | Y14: incomplete | Z14: mismatched_statements_replaced+appended_missing_items | AA14: 21 CFR 111.103; 21 CFR 111.105; 21 CFR 111.10(a); 21 CFR 111.110; 21 CFR 111.113(a); 21 CFR 111.117; 21 CFR 111.120; 21 CFR 111.123(a); 21 CFR 111.127; 21 CFR 111.12(a); 21 CFR 111.130; 21 CFR 111.135; 21 CFR 111.13(a); 21 CFR 111.140(a); 21 CFR 111.14(a); 21 CFR 111.153; 21 CFR 111.155(a); 21 CFR 111.15(a); 21 CFR 111.160(a); 21 CFR 111.165(a); 21 CFR 111.16 | AC14: Under Part 111, the representative samples must be collected under 21 CFR 111.103 [1], which outlines the requirements for written procedures. Quality control personnel must ensure the quality of dietary supplements through written procedures, including conducting material reviews and making disposition decisions [2]. The reserve sample requirements apply under 21 CFR 111.105 [1], which mandates ensuring the quality of the dietary supplement through operations that include packaging and labeling. The quality control operations required for laboratory operations associated with the production and process control system must include material reviews and disposition decisions [4]. The quality control operations for equipment, instruments, and controls must include these activities [6]. The quality control operations for components, packaging, and labels before use in the manufacture of a dietary supplement must include these activities [7]. The quality control operations for the master manufacturing record, the batch production record, and manufacturing operations must include these activities [8]. The quality control operations for packaging and labeling operations must include these activities [9]. The personnel qualification requirements apply under 21 CFR 111.10(a) [10], which requires qualified employees to supervise the manufacturing, packaging, labeling, or holding of dietary supplements. The records required under this subpart F must be made and kept in accordance with subpart P of this part [14]. The records required under this subpart B must be made and kept in accordance with subpart P of this part [15]. The written procedures for fulfilling the requirements of this subpart G must be established and followed [16]. The requirements under this subpart G apply to components of dietary supplements [17]. The sanitation requirements apply to the physical plant and grounds [18]. The requirements under this subpart G apply to packaging and labels received [19]. The requirements under this subpart G apply to a product received for packaging or labeling as a dietary supplement [20]. The requirements under this subpart C for written procedures include cleaning the physical plant and pest control [21]. | AD14: unmarked | AE14: 14
A15: S-014 | B15: Dietary Supplements — 21 CFR 111 | C15: Direct Lookup | D15: Intermediate | E15: What must quality control personnel do under Part 111? | F15: [DRAFT KEY - NOT SME-VERIFIED] Review and approve/reject, review records, perform material review and disposition, approve deviations and reprocessing. | G15: Under Part 111, quality control personnel must establish and follow written procedures for the responsibilities of the quality control operations, including written procedures for conducting a material review and making a disposition decision, and for approving or rejecting any reprocessing. [1] Quality control personnel must ensure that your manufacturing, packaging, labeling, and holding operations ensure the quality of the dietary supplement and that the dietary supplement is packaged and labeled as specified in the master manufacturing record. To do so, quality control personnel must perform operations that include: [2] Quality control personnel must conduct a material review and make a disposition decision if: [5] | H15: 21 CFR 111.105 | I15: Part 111, 21 CFR 111.103, 21 CFR 111.105, 21 CFR 111.113(a) | J15: draft section cited | K15: 23.02 | L15: OK | M15: FAIL | O15: Citations to 111.103, 111.105 and 111.113(a) are appropriate, but the answer is three dangling lead-ins ending in colons: it never states what quality-control personnel must actually do (approve or reject processes and specifications, review records, approve deviations and reprocessing). | P15: Draft key 111.105 verified correct. Fails on substance and completeness, not citation. || MACHINE CHECKS: no machine indicators | Q15: N | R15: 1 | S15: 0 | T15: 1 | U15: 0 | V15: 1 | X15: ANSWERABLE | Y15: valid | AA15: 21 CFR 111.103; 21 CFR 111.105; 21 CFR 111.10(a); 21 CFR 111.110; 21 CFR 111.113(a); 21 CFR 111.117; 21 CFR 111.120; 21 CFR 111.123(a); 21 CFR 111.127; 21 CFR 111.12(a); 21 CFR 111.130; 21 CFR 111.135; 21 CFR 111.13(a); 21 CFR 111.140(a); 21 CFR 111.14(a); 21 CFR 111.153; 21 CFR 111.155(a); 21 CFR 111.15(a); 21 CFR 111.160(a); 21 CFR 111.165(a); 21 CFR 111.16 | AC15: Under Part 111, quality control personnel must establish and follow written procedures for the responsibilities of the quality control operations, including written procedures for conducting a material review and making a disposition decision, and for approving or rejecting any reprocessing. [1] Quality control personnel must ensure that your manufacturing, packaging, labeling, and holding operations ensure the quality of the dietary supplement and that the dietary supplement is packaged and labeled as specified in the master manufacturing record. To do so, quality control personnel must perform operations that include: [2] Quality control personnel must conduct a material review and make a disposition decision if: [5] Quality control personnel must conduct a material review and make a disposition decision if [5] Quality control personnel must ensure that your manufacturing, packaging, labeling, and holding operations ensure the quality of the dietary supplement and that the dietary supplement is packaged and labeled as specified in the master manufacturing record. To do so, quality control personnel must perform operations that include: [2] | AD15: unmarked | AE15: 15
A16: S-015 | B16: Dietary Supplements — 21 CFR 111 | C16: Distinction | D16: Advanced | E16: Under Part 111, what is the difference between the responsibilities of quality control personnel and those of production personnel? | F16: [DRAFT KEY - NOT SME-VERIFIED] QC independence, approval authority, separation of duties, no self-approval of own work. | G16: Under Part 111, the responsibilities of quality control personnel include ensuring the quality of dietary supplements through written procedures for conducting material reviews, making disposition decisions, and approving or rejecting reprocessing. Quality control personnel must also ensure the quality of the dietary supplement and packaging, labeling, and holding operations, including performing operations that involve material reviews and disposition decisions. They must prevent microbial contamination by excluding sick or infected personnel and implementing hygienic practices. Quality control operations for laboratory operations associated with the production and process control system must include material reviews and disposition decisions. Quality control operations for equipment, instruments, and controls must include these activities. Quality control operations for components, packaging, and labels before use in the manufacture of a dietary supplement must include these activities. Quality control operations for the master manufacturing record, the batch production record, and manufacturing operations must include these activities. Quality control operations for packaging and labeling operations must include these activities. Personnel qualification requirements apply, and supervisor requirements apply. The records required under this subpart F must be made and kept in accordance with subpart P of this part. The records required under this subpart B must be made and kept in accordance with subpart P of this part. The requirements under this subpart G for written procedures include establishing and following written procedures. The requirements under this subpart F for preventing microbial contamination include excluding sources of microbial contamination and implementing hygienic practices. The requirements under this subpart G for components of dietary supplements include visual examination of containers for appropriate content labels, container damage, or broken seals. The requirements under this subpart F for sanitation requirements apply to the physical plant and grounds. The requirements under this subpart F for packaging and labels received must include visual examination of containers for appropriate content labels, container damage, or broken seals. | H16: 21 CFR 111.105; cross-ref 111.12 | I16: Part 111 | J16: same part, different section | K16: 40.7 | L16: OK | M16: FAIL | O16: Never states the distinction asked for (quality-control independence, approval authority, separation of duties, no self-approval). Circular list of 'operations must include these activities' with no citation markers at all. | P16: Draft key 111.105 + 111.12 verified correct. The separation-of-duties rule in 111.12(b) was in the retrieved evidence but not used. || MACHINE CHECKS: indicator: citation vs draft key: same part, different section | pipeline validator codes on raw output: unsupported_claim, repeated_statement | Q16: N | R16: 0 | S16: 0 | T16: 1 | U16: 0 | V16: 1 | X16: ANSWERABLE | Y16: valid | AA16: 21 CFR 111.103; 21 CFR 111.105; 21 CFR 111.10(a); 21 CFR 111.110; 21 CFR 111.113(a); 21 CFR 111.117; 21 CFR 111.120; 21 CFR 111.123(a); 21 CFR 111.127; 21 CFR 111.12(a); 21 CFR 111.130; 21 CFR 111.135; 21 CFR 111.13(a); 21 CFR 111.140(a); 21 CFR 111.14(a); 21 CFR 111.153; 21 CFR 111.155(a); 21 CFR 111.15(a); 21 CFR 111.160(a); 21 CFR 111.165(a); 21 CFR 111.16 | AC16: Under Part 111, the responsibilities of quality control personnel include ensuring the quality of dietary supplements through written procedures for conducting material reviews, making disposition decisions, and approving or rejecting reprocessing. Quality control personnel must also ensure the quality of the dietary supplement and packaging, labeling, and holding operations, including performing operations that involve material reviews and disposition decisions. They must prevent microbial contamination by excluding sick or infected personnel and implementing hygienic practices. Quality control operations for laboratory operations associated with the production and process control system must include material reviews and disposition decisions. Quality control operations for equipment, instruments, and controls must include these activities. Quality control operations for components, packaging, and labels before use in the manufacture of a dietary supplement must include these activities. Quality control operations for the master manufacturing record, the batch production record, and manufacturing operations must include these activities. Quality control operations for packaging and labeling operations must include these activities. Personnel qualification requirements apply, and supervisor requirements apply. The records required under this subpart F must be made and kept in accordance with subpart P of this part. The records required under this subpart B must be made and kept in accordance with subpart P of this part. The requirements under this subpart G for written procedures include establishing and following written procedures. The requirements under this subpart F for preventing microbial contamination include excluding sources of microbial contamination and implementing hygienic practices. The requirements under this subpart G for components of dietary supplements include visual examination of containers for appropriate content labels, container damage, or broken seals. The requirements under this subpart F for sanitation requirements apply to the physical plant and grounds. The requirements under this subpart F for packaging and labels received must include visual examination of containers for appropriate content labels, container damage, or broken seals. | AD16: unmarked | AE16: 16
A17: S-016 | B17: Dietary Supplements — 21 CFR 111 | C17: Direct Lookup | D17: Intermediate | E17: What requirements apply to components, packaging, and labels before use in dietary supplement manufacturing? | F17: [DRAFT KEY - NOT SME-VERIFIED] Identity verification of each component, supplier COA reliance conditions, quarantine, rejection of unsuitable materials. | G17: The available regulatory sources do not provide enough information to answer this question. [1] | H17: 21 CFR 111.155; 111.160 | I17: 21 CFR 111.170 | J17: same part, different section | K17: 4.38 | L17: OK | M17: FAIL | O17: Wrongly declines ('sources do not provide enough information') although 111.155 and 111.160 exist and were in the retrieved evidence; cites 111.170. Identity verification, quarantine and rejection requirements are never given. | P17: Draft key 111.155/111.160 verified correct against the snapshot. Safe but incorrect: an answerable question left unanswered. || MACHINE CHECKS: indicator: citation vs draft key: same part, different section | Q17: N | R17: 0 | S17: 0 | T17: 0 | U17: 0 | V17: 1 | X17: UNKNOWN | Y17: valid | AA17: 21 CFR 111.170; 21 CFR 111.20(c)(2); 21 CFR 111.20(c)(1); 21 CFR 111.27(d); FDA Guidance: Guidance for Industry: Foreign Supplier Verification Programs for Importers of Food for Humans and Animals (final, 2023-01-10, Docket FDA-2017-D-5225) | AC17: The available regulatory sources do not provide enough information to answer this question. [1] | AD17: unmarked | AE17: 17
A18: S-017 | B18: Dietary Supplements — 21 CFR 111 | C18: Application | D18: Advanced | E18: A firm wants to rely on a supplier certificate of analysis instead of testing a component for identity. Is that allowed? | F18: [DRAFT KEY - NOT SME-VERIFIED] Identity test of a dietary ingredient by the manufacturer is required; COA reliance permitted for other component specs only after qualifying the supplier and periodic reconfirmation. | G18: The available regulatory sources do not provide enough information to answer this question. The question is about whether a firm can rely on a supplier certificate of analysis instead of testing a component for identity, but no specific provision is provided in the evidence. The evidence includes guidance on supplier verification activities and blood donation testing, but none directly address the use of supplier certificates of analysis. The sources do not provide a clear answer to the question. | H18: 21 CFR 111.75(a)(1)-(2); 111.155 | I18: none | J18: no CFR citation | K18: 10.03 | L18: OK | M18: FAIL | O18: Declines the question. 111.75(a)(1)(i) requires the manufacturer's own identity test for a dietary ingredient and 111.75(a)(2) sets the conditions for relying on a supplier's certificate for other specifications; neither is stated. | P18: Draft key 111.75(a)(1)-(2) + 111.155 verified correct. No fabrication and scope discipline intact, but the regulatory answer is missing. || MACHINE CHECKS: indicator: citation vs draft key: no CFR citation | Q18: N | R18: 0 | S18: 0 | T18: 0 | U18: 0 | V18: 1 | X18: UNKNOWN | Y18: valid | AA18: FDA Guidance: CVM GFI #246 Hazard Analysis and Risk-Based Preventive Controls for Food for Animals: Supply-Chain Program (draft, 2018-06-15, Docket FDA-2018-D-1861); FDA Guidance: Recommendations for Screening, Testing, and Management of Blood Donors and Blood and Blood Components Based on Screening Tests for Syphilis: Guidance for Industry (final, 2020-12-02, Docket FDA-2003-D-0128); 21 CFR 660.54(a) | AC18: The available regulatory sources do not provide enough information to answer this question. The question is about whether a firm can rely on a supplier certificate of analysis instead of testing a component for identity, but no specific provision is provided in the evidence. The evidence includes guidance on supplier verification activities and blood donation testing, but none directly address the use of supplier certificates of analysis. The sources do not provide a clear answer to the question. | AD18: unmarked | AE18: 18
A19: S-018 | B19: Dietary Supplements — 21 CFR 111 | C19: Direct Lookup | D19: Basic | E19: What must the master manufacturing record include under Part 111? | F19: [DRAFT KEY - NOT SME-VERIFIED] Name/strength/concentration, batch size, complete list of components, accurate statement of weight/measure, identity statement, procedures, specifications at each point, in-process controls, packaging/labeling. | G19: The generated answer could not be validated against the retrieved regulatory evidence, so it is not shown. The retrieved sources were not verified to answer the question as asked, so their text is not quoted as an answer. Sources consulted: 21 CFR 111.103, 21 CFR 111.105, 21 CFR 111.10(a), 21 CFR 111.110, 21 CFR 111.113(a) and 16 more. | H19: 21 CFR 111.210 | I19: none (answer withheld) | J19: no CFR citation | K19: 31.98 | L19: OK | M19: FAIL | O19: No answer delivered: validation withheld the draft. None of 111.210's master manufacturing record contents are stated. | P19: Draft key 111.210 verified correct. Withheld draft recited quality-control operations instead of record contents. || MACHINE CHECKS: indicator: citation vs draft key: no CFR citation | indicator: answer withheld by validation (likely incomplete / no substantive answer) | pipeline validator codes on raw output: degenerate_output, truncated, low_overlap_with_cited_source, repeated_statement | Q19: N | R19: 0 | S19: 0 | T19: 0 | U19: 0 | V19: 1 | X19: ANSWERABLE | Y19: unsupported | Z19: unvalidated_answer_withheld | AA19: 21 CFR 111.103; 21 CFR 111.105; 21 CFR 111.10(a); 21 CFR 111.110; 21 CFR 111.113(a); 21 CFR 111.117; 21 CFR 111.120; 21 CFR 111.123(a); 21 CFR 111.127; 21 CFR 111.12(a); 21 CFR 111.130; 21 CFR 111.135; 21 CFR 111.13(a); 21 CFR 111.140(a); 21 CFR 111.14(a); 21 CFR 111.153; 21 CFR 111.155(a); 21 CFR 111.15(a); 21 CFR 111.160(a); 21 CFR 111.165(a); 21 CFR 111.16 | AC19: Under Part 111, the master manufacturing record must include requirements for quality control operations, including ensuring the quality of the dietary supplement and packaging, labeling, and holding operations. [1] The master manufacturing record must include quality control operations for the master manufacturing record, the batch production record, and manufacturing operations. [8] The master manufacturing record must include quality control operations for components, packaging, and labels before use in the manufacture of a dietary supplement. [7] The master manufacturing record must include quality control operations for packaging and labeling operations. [9] The master manufacturing record must include quality control operations for returned dietary supplements. [11] The master manufacturing record must include quality control operations for product complaints. [12] The master manufacturing record must include quality control operations for returned dietary supplements. [11] The master manufacturing record must include quality control operations for product complaints. [12] The master manufacturing record must include quality control operations for returned dietary supplements. [11 | AD19: unmarked | AE19: 19
A20: S-019 | B20: Dietary Supplements — 21 CFR 111 | C20: Cross-Reference | D20: Intermediate | E20: When is a master manufacturing record required, and how does it relate to the batch production record? | F20: [DRAFT KEY - NOT SME-VERIFIED] MMR required for each unique formulation and batch size; BPR must accurately follow the MMR. | G20: The master manufacturing record is required for quality control operations, and it must include reviewing and approving all batch production-related records. This requirement is specified in [1]. The batch production record is related to the master manufacturing record and must be maintained for at least 3 years after the batch of medical gas is distributed, as required by [2]. The foreign supplier verification program guidance also requires that the master manufacturing record for each formulation includes calculations for relative amounts of other components based on plant material, ensuring uniformity in finished batches, as per [3]. | H20: 21 CFR 111.205; 111.255 | I20: 21 CFR 111.123(a)(2) | J20: same part, different section | K20: 13.14 | L20: OK | M20: FAIL | O20: Materially misleading: applies a medical-gases draft guidance (3-year retention 'after the batch of medical gas is distributed') and the FSVP guidance to a dietary-supplement master manufacturing record, and cites 111.123(a)(2) for the record's contents. The actual rule - one record per unique formulation and batch size (111.205), with the batch record following it (111.255) - is absent. | P20: Draft key 111.205/111.255 verified correct. Cross-domain contamination of authorities; cited documents exist, so no fabrication. || MACHINE CHECKS: indicator: citation vs draft key: same part, different section | pipeline validator codes on raw output: invented_condition, qualifier_dropped | Q20: N | R20: 0 | S20: 0 | T20: 0 | U20: 0 | V20: 1 | X20: UNKNOWN | Y20: valid | Z20: invented_conditions_removed | AA20: 21 CFR 111.123(a)(2); FDA Guidance: Medical Gases — Current Good Manufacturing Practice: Draft Guidance for Industry (draft, 2025-11-28, Docket FDA-2003-D-0431); FDA Guidance: Guidance for Industry: Foreign Supplier Verification Programs for Importers of Food for Humans and Animals (final, 2023-01-10, Docket FDA-2017-D-5225) | AC20: The master manufacturing record is required for quality control operations, and it must include reviewing and approving all batch production-related records. This requirement is specified in [1]. The batch production record is related to the master manufacturing record and must be maintained for at least 3 years after the batch of medical gas is distributed, as required by [2]. The foreign supplier verification program guidance also requires that the master manufacturing record for each formulation includes calculations for relative amounts of other components based on plant material, ensuring uniformity in finished batches, as per [3]. If applicable, the requirement also limits the scope to ensure that the MMRs meet the standards for public protection as required by [2]. | AD20: unmarked | AE20: 20
A21: S-020 | B21: Dietary Supplements — 21 CFR 111 | C21: Direct Lookup | D21: Intermediate | E21: What must the batch production record contain under Part 111? | F21: [DRAFT KEY - NOT SME-VERIFIED] Batch/lot identification, identity/weight/measure of each component, dates and times, equipment used, initials of persons performing and verifying, results of tests, documentation of deviations. | G21: The generated answer could not be validated against the retrieved regulatory evidence, so it is not shown. The retrieved sources were not verified to answer the question as asked, so their text is not quoted as an answer. Sources consulted: 21 CFR 111.103, 21 CFR 111.105, 21 CFR 111.10(a), 21 CFR 111.110, 21 CFR 111.113(a) and 16 more. | H21: 21 CFR 111.260 | I21: none (answer withheld) | J21: no CFR citation | K21: 20.56 | L21: OK | M21: FAIL | O21: No answer delivered: validation withheld the draft. None of 111.260's batch record contents (batch number, components and quantities, equipment, dates, test results, deviations) are stated. | P21: Draft key 111.260 verified correct against the snapshot. || MACHINE CHECKS: indicator: citation vs draft key: no CFR citation | indicator: answer withheld by validation (likely incomplete / no substantive answer) | pipeline validator codes on raw output: degenerate_output, truncated, repeated_statement | Q21: N | R21: 0 | S21: 0 | T21: 0 | U21: 0 | V21: 1 | X21: ANSWERABLE | Y21: unsupported | Z21: unvalidated_answer_withheld | AA21: 21 CFR 111.103; 21 CFR 111.105; 21 CFR 111.10(a); 21 CFR 111.110; 21 CFR 111.113(a); 21 CFR 111.117; 21 CFR 111.120; 21 CFR 111.123(a); 21 CFR 111.127; 21 CFR 111.12(a); 21 CFR 111.130; 21 CFR 111.135; 21 CFR 111.13(a); 21 CFR 111.140(a); 21 CFR 111.14(a); 21 CFR 111.153; 21 CFR 111.155(a); 21 CFR 111.15(a); 21 CFR 111.160(a); 21 CFR 111.165(a); 21 CFR 111.16 | AC21: Under Part 111, the batch production record must include written procedures for conducting a material review and making a disposition decision, and for approving or rejecting any reprocessing [1]. Quality control personnel must ensure that your manufacturing, packaging, labeling, and holding operations ensure the quality of the dietary supplement and that the dietary supplement is packaged and labeled as specified in the master manufacturing record. To do so, quality control personnel must perform operations that include [1]. Quality control personnel must conduct a material review and make a disposition decision if [1]. Quality control personnel must conduct a material review and make a disposition decision if [1]. Quality control personnel must conduct a material review and make a disposition decision if [1]. Quality | AD21: unmarked | AE21: 21
A22: S-021 | B22: Dietary Supplements — 21 CFR 111 | C22: Direct Lookup | D22: Intermediate | E22: What must laboratory control processes include under Part 111? | F22: [DRAFT KEY - NOT SME-VERIFIED] Sample use, criteria for selecting test methods, sampling plans, criteria for accepting/rejecting test results. | G22: The generated answer could not be validated against the retrieved regulatory evidence, so it is not shown. The retrieved sources were not verified to answer the question as asked, so their text is not quoted as an answer. Sources consulted: 21 CFR 111.103, 21 CFR 111.105, 21 CFR 111.10(a), 21 CFR 111.110, 21 CFR 111.113(a) and 16 more. | H22: 21 CFR 111.310 | I22: none (answer withheld) | J22: no CFR citation | K22: 37.71 | L22: OK | M22: FAIL | O22: No answer delivered: validation withheld the draft, which recited quality-control procedure text. | P22: DRAFT KEY QUESTIONABLE: 111.310 in the snapshot is laboratory facilities; the key elements listed (sample use, method selection, sampling plans, accept/reject criteria) are the laboratory control processes section, 111.303. Immaterial here, since no answer was given. || MACHINE CHECKS: indicator: citation vs draft key: no CFR citation | indicator: answer withheld by validation (likely incomplete / no substantive answer) | pipeline validator codes on raw output: degenerate_output, truncated, uncited_statement, low_overlap_with_cited_source, repeated_statement | Q22: N | R22: 0 | S22: 0 | T22: 0 | U22: 0 | V22: 1 | X22: ANSWERABLE | Y22: unsupported | Z22: unvalidated_answer_withheld | AA22: 21 CFR 111.103; 21 CFR 111.105; 21 CFR 111.10(a); 21 CFR 111.110; 21 CFR 111.113(a); 21 CFR 111.117; 21 CFR 111.120; 21 CFR 111.123(a); 21 CFR 111.127; 21 CFR 111.12(a); 21 CFR 111.130; 21 CFR 111.135; 21 CFR 111.13(a); 21 CFR 111.140(a); 21 CFR 111.14(a); 21 CFR 111.153; 21 CFR 111.155(a); 21 CFR 111.15(a); 21 CFR 111.160(a); 21 CFR 111.165(a); 21 CFR 111.16 | AC22: Under Part 111, laboratory control processes must include written procedures for conducting a material review and making a disposition decision, and for approving or rejecting any reprocessing. [1] Under Part 111, quality control personnel must ensure that your manufacturing, packaging, labeling, and holding operations ensure the quality of the dietary supplement and that the dietary supplement is packaged and labeled as specified in the master manufacturing record. To do so, quality control personnel must perform operations that include: [1] Under Part 111, quality control personnel must ensure that your manufacturing, packaging, labeling, and holding operations ensure the quality of the dietary supplement and that the dietary supplement is packaged and labeled as specified in the master manufacturing record. To do so, quality control personnel must perform operations that include: [1] Under Part 111, quality control personnel must ensure that your manufacturing, packaging, labeling, and holding operations ensure the quality of the dietary supplement and that the dietary supplement is packaged and labeled as specified in the master manufacturing record. To do so, quality control personnel must perform operations that include: [1] Under Part 111, quality control personnel must ensure that your manufacturing, packaging, labeling, and holding operations ensure the quality of the dietary supplement and that the dietary supplement is packaged and labeled as specified in the master manufacturing record. To do so, quality control personnel must perform operations that | AD22: unmarked | AE22: 22
A23: S-022 | B23: Dietary Supplements — 21 CFR 111 | C23: Direct Lookup | D23: Advanced | E23: What requirements apply to laboratory methods for testing and examination under Part 111? | F23: [DRAFT KEY - NOT SME-VERIFIED] Methods must be appropriate and scientifically valid; verification of suitability for the matrix. | G23: Under Part 111, laboratory methods for testing and examination must establish and follow written procedures for conducting a material review and making a disposition decision, and for approving or rejecting any reprocessing. [1] Quality control personnel must ensure that your manufacturing, packaging, labeling, and holding operations ensure the quality of the dietary supplement and that the dietary supplement is packaged and labeled as specified in the master manufacturing record. To do so, quality control personnel must perform operations that include: [1] Quality control personnel must conduct a material review and make a disposition decision if: [1] Quality control operations for equipment, instruments, and controls must include: [1] Quality control operations for components, packaging, and labels before use in the manufacture of a dietary supplement must include: [1] Quality control operations for the master manufacturing record, the batch production record, and manufacturing operations must include: [1] Quality control operations for packaging and labeling operations must include: [1] You must have qualified employees who manufacture, package, label, or hold dietary supplements. [1] You must assign qualified personnel to supervise the manufacturing, packaging, labeling, or holding of dietary supplements. [1] You must visually examine each immediate container or grouping of immediate containers in a shipment for appropriate content label, container damage, or broken seals to determine whether the container condition may have resulted in contamination or deterioration of the components. [17] You must visually examine each immediate container or grouping of immediate containers in a shipment for appropriate content label, container damage, or broken seals to determine whether the container condition may have resulted in contamination or deterioration of the packaging and labels. [19] You must visually examine each immediate container or grouping of immediate containers in a shipment for appropriate content label, container damage, or broken seals to determine whether the container condition may have resulted in contamination or deterioration of the received product. [20] The available regulatory sources do not provide enough information to answer this. [9] | H23: 21 CFR 111.320 | I23: Part 111, 21 CFR 111.103, 21 CFR 111.127, 21 CFR 111.155(a), 21 CFR 111.160(a), 21 CFR 111.165(a) | J23: same part, different section | K23: 56.42 | L23: OK | M23: FAIL | O23: Returns quality-control and receiving-inspection text cited to 111.103 and others; never states 111.320's requirements that methods be verified as appropriate and scientifically valid. | P23: Draft key 111.320 verified correct against the snapshot. || MACHINE CHECKS: indicator: citation vs draft key: same part, different section | pipeline validator codes on raw output: low_overlap_with_cited_source, repeated_statement | Q23: N | R23: 0 | S23: 0 | T23: 0 | U23: 0 | V23: 1 | X23: ANSWERABLE | Y23: valid | AA23: 21 CFR 111.103; 21 CFR 111.105; 21 CFR 111.10(a); 21 CFR 111.110; 21 CFR 111.113(a); 21 CFR 111.117; 21 CFR 111.120; 21 CFR 111.123(a); 21 CFR 111.127; 21 CFR 111.12(a); 21 CFR 111.130; 21 CFR 111.135; 21 CFR 111.13(a); 21 CFR 111.140(a); 21 CFR 111.14(a); 21 CFR 111.153; 21 CFR 111.155(a); 21 CFR 111.15(a); 21 CFR 111.160(a); 21 CFR 111.165(a); 21 CFR 111.16 | AC23: Under Part 111, laboratory methods for testing and examination must establish and follow written procedures for conducting a material review and making a disposition decision, and for approving or rejecting any reprocessing. [1] Quality control personnel must ensure that your manufacturing, packaging, labeling, and holding operations ensure the quality of the dietary supplement and that the dietary supplement is packaged and labeled as specified in the master manufacturing record. To do so, quality control personnel must perform operations that include: [1] Quality control personnel must conduct a material review and make a disposition decision if: [1] Quality control operations for equipment, instruments, and controls must include: [1] Quality control operations for components, packaging, and labels before use in the manufacture of a dietary supplement must include: [1] Quality control operations for the master manufacturing record, the batch production record, and manufacturing operations must include: [1] Quality control operations for packaging and labeling operations must include: [1] You must have qualified employees who manufacture, package, label, or hold dietary supplements. [1] You must assign qualified personnel to supervise the manufacturing, packaging, labeling, or holding of dietary supplements. [1] You must visually examine each immediate container or grouping of immediate containers in a shipment for appropriate content label, container damage, or broken seals to determine whether the container condition may have resulted in contamination or deterioration of the components. [17] You must visually examine each immediate container or grouping of immediate containers in a shipment for appropriate content label, container damage, or broken seals to determine whether the container condition may have resulted in contamination or deterioration of the packaging and labels. [19] You must visually examine each immediate container or grouping of immediate containers in a shipment for appropriate content label, container damage, or broken seals to determine whether the container condition may have resulted in contamination or deterioration of the received product. [20] The available regulatory sources do not provide enough information to answer this. [9] | AD23: unmarked | AE23: 23
A24: S-023 | B24: Dietary Supplements — 21 CFR 111 | C24: Direct Lookup | D24: Intermediate | E24: What manufacturing operations requirements apply under Part 111 to prevent contamination? | F24: [DRAFT KEY - NOT SME-VERIFIED] Sanitation, protection against contamination, control of physical/chemical/microbial hazards during manufacturing. | G24: Under Part 111, manufacturing operations requirements apply to prevent contamination. Quality control personnel must establish and follow written procedures for conducting a material review and making a disposition decision, and for approving or rejecting any reprocessing. Preventing microbial contamination requires excluding sources of contamination, including sick or infected personnel, and includes measures such as cleaning and disinfecting. Quality control operations for laboratory operations must include material reviews and disposition decisions. Quality control operations for equipment, instruments, and controls must include these requirements. Quality control operations for components, packaging, and labels before use must include these requirements. Quality control operations for the master manufacturing record, the batch production record, and manufacturing operations must include these requirements. Quality control operations for packaging and labeling operations must include these requirements. Supervisors must be qualified to supervise the manufacturing, packaging, labeling, or holding of dietary supplements. Records required under this subpart must be kept in accordance with subpart P of this part. | H24: 21 CFR 111.365 | I24: Part 111 | J24: same part, different section | K24: 22.15 | L24: OK | M24: FAIL | O24: Mentions excluding sick personnel and hygiene (111.10 material, not 111.365) and otherwise recycles quality-control phrasing. Water quality, contamination testing, sterilising/pasteurising and microbial-growth controls are omitted, and no citation markers are given. | P24: Draft key 111.365 verified correct against the snapshot. || MACHINE CHECKS: indicator: citation vs draft key: same part, different section | Q24: N | R24: 0 | S24: 0 | T24: 1 | U24: 0 | V24: 1 | X24: ANSWERABLE | Y24: valid | AA24: 21 CFR 111.103; 21 CFR 111.105; 21 CFR 111.10(a); 21 CFR 111.110; 21 CFR 111.113(a); 21 CFR 111.117; 21 CFR 111.120; 21 CFR 111.123(a); 21 CFR 111.127; 21 CFR 111.12(a); 21 CFR 111.130; 21 CFR 111.135; 21 CFR 111.13(a); 21 CFR 111.140(a); 21 CFR 111.14(a); 21 CFR 111.153; 21 CFR 111.155(a); 21 CFR 111.15(a); 21 CFR 111.160(a); 21 CFR 111.165(a); 21 CFR 111.16 | AC24: Under Part 111, manufacturing operations requirements apply to prevent contamination. Quality control personnel must establish and follow written procedures for conducting a material review and making a disposition decision, and for approving or rejecting any reprocessing. Preventing microbial contamination requires excluding sources of contamination, including sick or infected personnel, and includes measures such as cleaning and disinfecting. Quality control operations for laboratory operations must include material reviews and disposition decisions. Quality control operations for equipment, instruments, and controls must include these requirements. Quality control operations for components, packaging, and labels before use must include these requirements. Quality control operations for the master manufacturing record, the batch production record, and manufacturing operations must include these requirements. Quality control operations for packaging and labeling operations must include these requirements. Supervisors must be qualified to supervise the manufacturing, packaging, labeling, or holding of dietary supplements. Records required under this subpart must be kept in accordance with subpart P of this part. | AD24: unmarked | AE24: 24
A25: S-024 | B25: Dietary Supplements — 21 CFR 111 | C25: Direct Lookup | D25: Intermediate | E25: What packaging and labeling operations requirements apply under Part 111? | F25: [DRAFT KEY - NOT SME-VERIFIED] Package/label suitability, label examination, filling/assembling/packaging controls, gang printing controls, label reconciliation. | G25: Under Part 111, packaging and labeling operations require written procedures for quality control, including ensuring the quality of the dietary supplement, packaging, labeling, and holding operations. Quality control personnel must ensure that the dietary supplement is packaged and labeled as specified in the master manufacturing record. They must perform operations that include material reviews and disposition decisions, and for equipment, instruments, and controls, they must include quality control operations. Packaging and labeling operations must include visual examination of containers for appropriate content labels, container damage, or broken seals to determine if contamination or deterioration may have occurred. The requirements apply to the master manufacturing record, batch production record, and manufacturing operations. | H25: 21 CFR 111.410; 111.415 | I25: Part 111 | J25: same part, different section | K25: 18.12 | L25: OK | M25: FAIL | O25: Container inspection content belongs to 111.155/111.160, not packaging operations. Label examination against the master manufacturing record, issuance and reconciliation controls, batch numbering and separation of operations (111.410, 111.415) are omitted; no citation markers. | P25: Draft key 111.410/111.415 verified correct against the snapshot. || MACHINE CHECKS: indicator: citation vs draft key: same part, different section | pipeline validator codes on raw output: uncited_statement, low_overlap_with_cited_source, invented_condition | Q25: N | R25: 0 | S25: 0 | T25: 1 | U25: 0 | V25: 1 | X25: ANSWERABLE | Y25: valid | Z25: invented_conditions_removed | AA25: 21 CFR 111.103; 21 CFR 111.105; 21 CFR 111.10(a); 21 CFR 111.110; 21 CFR 111.113(a); 21 CFR 111.117; 21 CFR 111.120; 21 CFR 111.123(a); 21 CFR 111.127; 21 CFR 111.12(a); 21 CFR 111.130; 21 CFR 111.135; 21 CFR 111.13(a); 21 CFR 111.140(a); 21 CFR 111.14(a); 21 CFR 111.153; 21 CFR 111.155(a); 21 CFR 111.15(a); 21 CFR 111.160(a); 21 CFR 111.165(a); 21 CFR 111.16 | AC25: Under Part 111, packaging and labeling operations require written procedures for quality control, including ensuring the quality of the dietary supplement, packaging, labeling, and holding operations. Quality control personnel must ensure that the dietary supplement is packaged and labeled as specified in the master manufacturing record. They must perform operations that include material reviews and disposition decisions, and for equipment, instruments, and controls, they must include quality control operations. Packaging and labeling operations must include visual examination of containers for appropriate content labels, container damage, or broken seals to determine if contamination or deterioration may have occurred. The requirements apply to the master manufacturing record, batch production record, and manufacturing operations. If applicable, personnel qualifications and records must be maintained. [1] | AD25: unmarked | AE25: 25
A26: S-025 | B26: Dietary Supplements — 21 CFR 111 | C26: Direct Lookup | D26: Intermediate | E26: What holding and distributing requirements apply under Part 111? | F26: [DRAFT KEY - NOT SME-VERIFIED] Holding under appropriate conditions, holding of reserve samples, distribution under conditions protecting against deterioration. | H26: 21 CFR 111.453; 111.455; 111.465 | K26: 17.29 | L26: ERROR | M26: ERROR | N26: QueryCanceled: canceling statement due to statement timeout | O26: Not evaluable: the database cancelled a guidance full-text query (statement timeout) during retrieval, so no model answer exists. Technical execution failure, not a model-quality result. | P26: Recorded once and not retried, per the test protocol. Re-run this single question to obtain a scorable answer. | Q26: N | AD26: unmarked | AE26: 26
A27: S-026 | B27: Dietary Supplements — 21 CFR 111 | C27: Application | D27: Advanced | E27: A distributor returns a dietary supplement. What does Part 111 require the manufacturer to do with it? | F27: [DRAFT KEY - NOT SME-VERIFIED] Identify and quarantine, QC review, destruction or reprocessing conditions, salvage limits, investigation of other batches. | G27: Part 111 requires the manufacturer to establish and follow written procedures for the responsibilities of the quality control operations, including written procedures for conducting a material review and making a disposition decision, and for approving or rejecting any reprocessing. [1] | H27: 21 CFR 111.510; 111.515; 111.520; 111.525 | I27: Part 111, 21 CFR 111.103 | J27: same part, different section | K27: 9.51 | L27: OK | M27: FAIL | O27: Gives a generic written-procedures answer cited to 111.103. The actual requirements - identify and quarantine the return until quality-control review (111.510), destroy it unless salvage or reprocessing is approved (111.515, 111.520), and meet product specifications on reprocessing (111.525) - are absent. | P27: Draft key 111.510-111.525 verified correct against the snapshot. || MACHINE CHECKS: indicator: citation vs draft key: same part, different section | Q27: N | R27: 0 | S27: 0 | T27: 1 | U27: 0 | V27: 1 | X27: ANSWERABLE | Y27: valid | AA27: 21 CFR 111.103; 21 CFR 111.105; 21 CFR 111.10(a); 21 CFR 111.110; 21 CFR 111.113(a); 21 CFR 111.117; 21 CFR 111.120; 21 CFR 111.123(a); 21 CFR 111.127; 21 CFR 111.12(a); 21 CFR 111.130; 21 CFR 111.135; 21 CFR 111.13(a); 21 CFR 111.140(a); 21 CFR 111.14(a); 21 CFR 111.153; 21 CFR 111.155(a); 21 CFR 111.15(a); 21 CFR 111.160(a); 21 CFR 111.165(a); 21 CFR 111.16 | AC27: Part 111 requires the manufacturer to establish and follow written procedures for the responsibilities of the quality control operations, including written procedures for conducting a material review and making a disposition decision, and for approving or rejecting any reprocessing. [1] | AD27: unmarked | AE27: 27
A28: S-027 | B28: Dietary Supplements — 21 CFR 111 | C28: Application | D28: Intermediate | E28: What must a firm do when it receives a product complaint about a dietary supplement? | F28: [DRAFT KEY - NOT SME-VERIFIED] QC personnel review, determine whether complaint involves a possible CGMP failure, investigate, record required information. | G28: A firm must label a dietary supplement as a dietary supplement and intend it for ingestion. It must not be represented for use as a conventional food or as a sole item of a meal or the diet. Additionally, if the retailer's name appears on the label, they may authorize the manufacturer or packer to submit adverse event reports to the FDA. If the retailer's name does not appear on the label, they are not required to submit reports unless they have entered into an agreement with the manufacturer or packer. [1] | H28: 21 CFR 111.553; 111.560 | I28: none | J28: no CFR citation | K28: 28.71 | L28: OK | M28: FAIL | O28: Answers with dietary-supplement labelling and retailer adverse-event reporting text drawn from an FDA guidance. The qualified-person review, the possible-CGMP-failure determination and the investigation duty (111.560) are never mentioned. | P28: Draft key 111.553/111.560 verified correct. Guidance cited where a binding Part 111 requirement was asked for. || MACHINE CHECKS: indicator: citation vs draft key: no CFR citation | pipeline validator codes on raw output: invalid_citation | Q28: N | R28: 0 | S28: 0 | T28: 0 | U28: 0 | V28: 1 | X28: UNKNOWN | Y28: valid | Z28: invalid_citations_removed | AA28: FDA Guidance: Guidance for Industry: Questions and Answers Regarding Adverse Event Reporting and Recordkeeping for Dietary Supplements as Required by the Dietary Supplement and Nonprescription Drug Consumer Protection Act (final, 2013-09-01, Docket FDA-2007-D-0372); FDA Guidance: Guidance for Industry: Questions and Answers Regarding Adverse Event Reporting and Recordkeeping for Dietary Supplements as Required by the Dietary Supplement and Nonprescription Drug Consumer Protection Act (final, 2013-09-01, Docket FDA-2007-D-0372) | AC28: A firm must label a dietary supplement as a dietary supplement and intend it for ingestion. It must not be represented for use as a conventional food or as a sole item of a meal or the diet. Additionally, if the retailer's name appears on the label, they may authorize the manufacturer or packer to submit adverse event reports to the FDA. If the retailer's name does not appear on the label, they are not required to submit reports unless they have entered into an agreement with the manufacturer or packer. [1] [4] | AD28: unmarked | AE28: 28
A29: S-028 | B29: Dietary Supplements — 21 CFR 111 | C29: Direct Lookup | D29: Basic | E29: How long must Part 111 records be retained and how must they be made available? | F29: [DRAFT KEY - NOT SME-VERIFIED] Retention period tied to date of manufacture/expiration; available for FDA inspection and copying; original or true copy. | G29: Part 111 records must be retained for a period of at least 5 years, and they must be made available in a format that allows for easy access and retrieval. [1] The retrieved evidence does not establish the time period or frequency asked for. | H29: 21 CFR 111.605; 111.610 | I29: Part 111, 21 CFR 111.103 | J29: same part, different section | K29: 9.16 | L29: OK | M29: FAIL | O29: States a retention period of 'at least 5 years', which appears nowhere in Part 111: 111.605(a) requires 1 year past the shelf life date or 2 years beyond distribution of the last associated batch. An invented period, cited to 111.103, and the answer then contradicts itself by saying the evidence does not establish a period. | P29: Draft key 111.605/111.610 verified correct against the snapshot. A fabricated retention period is a material regulatory error. || MACHINE CHECKS: indicator: citation vs draft key: same part, different section | pipeline validator codes on raw output: low_overlap_with_cited_source, unsupported_claim | Q29: N | R29: 0 | S29: 0 | T29: 0 | U29: 0 | V29: 1 | X29: PARTIALLY_ANSWERABLE | Y29: valid | AA29: 21 CFR 111.103; 21 CFR 111.105; 21 CFR 111.10(a); 21 CFR 111.110; 21 CFR 111.113(a); 21 CFR 111.117; 21 CFR 111.120; 21 CFR 111.123(a); 21 CFR 111.127; 21 CFR 111.12(a); 21 CFR 111.130; 21 CFR 111.135; 21 CFR 111.13(a); 21 CFR 111.140(a); 21 CFR 111.14(a); 21 CFR 111.153; 21 CFR 111.155(a); 21 CFR 111.15(a); 21 CFR 111.160(a); 21 CFR 111.165(a); 21 CFR 111.16 | AC29: Part 111 records must be retained for a period of at least 5 years, and they must be made available in a format that allows for easy access and retrieval. [1] | AD29: unmarked | AE29: 29
A30: F-001 | B30: Human Food — 21 CFR 117 | C30: Direct Lookup | D30: Basic | E30: Who is subject to 21 CFR Part 117 and what are the principal exemptions? | F30: [DRAFT KEY - NOT SME-VERIFIED] Exemptions for certain facilities/activities, juice and seafood HACCP, low-risk on-farm activities, qualified facilities. | G30: [1] The management of the establishment must take reasonable measures and precautions to ensure the following: [1] [2] The manufacturer, processor, packer, and holder of food must at all times utilize quality control operations that reduce natural or unavoidable defects to the lowest level currently feasible [2] [3]. The requirement for a food safety plan [3] [4]. The requirement for a hazard analysis [4] [5]. The requirement for preventive controls [5] [6]. Circumstances in which the owner, operator, or agent in charge of a manufacturing/processing facility is not required to implement a preventive control [6] [7]. For food with a hazard requiring a preventive control: [8] [9] Preventive control management components [9] [10]. Monitoring [10] [11]. Corrective actions and corrections [11] [12]. Verification [12] [13]. Validation [13] [14]. Verification of implementation and effectiveness [14] [15]. Reanalysis [15] [16]. One or more preventive controls qualified individuals must do or oversee the following: [16] [17] Implementation records required for this subpart [17] [18]. Applicability and status [18] [19]. Attestations to be submitted [19] [20]. Modified requirements that apply to a qualified facility [20] [21]. Grounds [21] [22]. Circumstances that may lead FDA to withdraw a qualified facility exemption [22] [23]. Issuance of an order to withdraw a qualified facility exemption [23]. | H30: 21 CFR 117.5 | I30: 21 CFR 117.10, 21 CFR 117.110(a), 21 CFR 117.126(a), 21 CFR 117.130(a), 21 CFR 117.135(a)(1), 21 CFR 117.136(a), 21 CFR 117.137, 21 CFR 117.139, 21 CFR 117.140(a), 21 CFR 117.145, 21 CFR 117.150(a), 21 CFR 117.155(a), 21 CFR 117.160(a), 21 CFR 117.165(a), 21 CFR 117.170(a), 21 CFR 117.180(a), 21 CFR 117.190(a), 21 CFR 117.1(a), 21 CFR 117.201(a), 21 CFR 117.206(a), 21 CFR 117.20(a), 21 CFR 117.251(a), 21 CFR 117.254(a) | J30: same part, different section | K30: 71.36 | L30: OK | M30: FAIL | O30: Returns a numbered list of Part 117 section headings with no content. Neither who is subject nor any of the principal 117.5 exemptions (qualified facility, part 123 seafood, part 120 juice, low-risk on-farm activities) is stated. | P30: Draft key 117.5 verified correct against the snapshot. || MACHINE CHECKS: indicator: citation vs draft key: same part, different section | pipeline validator codes on raw output: provision_citation_mismatch, low_overlap_with_cited_source | Q30: N | R30: 0 | S30: 0 | T30: 0 | U30: 0 | V30: 1 | X30: ANSWERABLE | Y30: valid | Z30: mismatched_statements_replaced | AA30: 21 CFR 117.10; 21 CFR 117.110(a); 21 CFR 117.126(a); 21 CFR 117.130(a); 21 CFR 117.135(a)(1); 21 CFR 117.136(a); 21 CFR 117.137; 21 CFR 117.139; 21 CFR 117.140(a); 21 CFR 117.145; 21 CFR 117.150(a); 21 CFR 117.155(a); 21 CFR 117.160(a); 21 CFR 117.165(a); 21 CFR 117.170(a); 21 CFR 117.180(a); 21 CFR 117.190(a); 21 CFR 117.1(a); 21 CFR 117.201(a); 21 CFR 117.206(a); 21 CFR 117.20(a); 21 CFR 117.251(a); 21 CFR 117.254(a) | AC30: [1] The management of the establishment must take reasonable measures and precautions to ensure the following: [1] [2] The manufacturer, processor, packer, and holder of food must at all times utilize quality control operations that reduce natural or unavoidable defects to the lowest level currently feasible. [2] [3] The requirement for a food safety plan. [3] [4] The requirement for a hazard analysis. [4] [5] The requirement for preventive controls. [5] [6] Circumstances in which the owner, operator, or agent in charge of a manufacturing/processing facility is not required to implement a preventive control. [6] [7] A facility that provides a written assurance under § 117.136(a)(2), (3), or (4) must act consistently with the assurance and document its actions taken to satisfy the written assurance. [7] [8] For food with a hazard requiring a preventive control: [8] [9] Preventive control management components. [9] [10] Monitoring. [10] [11] Corrective actions and corrections. [11] [12] Verification. [12] [13] Validation. [13] [14] Verification of implementation and effectiveness. [14] [15] Reanalysis. [15] [16] One or more preventive controls qualified individuals must do or oversee the following: [16] [17] Implementation records required for this subpart. [17] [18] Applicability and status. [18] [19] Attestations to be submitted. [19] [20] Modified requirements that apply to a qualified facility. [20] [21] Grounds. [21] [22] Circumstances that may lead FDA to withdraw a qualified facility exemption. [22] [23] Issuance of an order to withdraw a qualified facility exemption. [23] | AD30: unmarked | AE30: 30
A31: F-002 | B31: Human Food — 21 CFR 117 | C31: Distinction | D31: Intermediate | E31: What is a 'qualified facility' under Part 117 and what modified requirements apply to one? | F31: [DRAFT KEY - NOT SME-VERIFIED] Definition tied to average annual sales thresholds, modified requirements in lieu of a full food safety plan. | G31: The generated answer could not be validated against the retrieved regulatory evidence, so it is not shown. The retrieved sources were not verified to answer the question as asked, so their text is not quoted as an answer. Sources consulted: 21 CFR 117.10, 21 CFR 117.110(a), 21 CFR 117.126(a), 21 CFR 117.130(a), 21 CFR 117.135(a)(1) and 18 more. | H31: 21 CFR 117.3; 117.5(a); Subpart D | I31: none (answer withheld) | J31: no CFR citation | K31: 61.46 | L31: OK | M31: FAIL | O31: No answer delivered: validation withheld the draft. The qualified-facility sales thresholds in 117.3 and the modified requirements of 117.201 are never given. | P31: Draft key 117.3/117.5(a)/Subpart D verified correct. The withheld draft had confused qualified facilities with unexposed-packaged-food storage. || MACHINE CHECKS: indicator: citation vs draft key: no CFR citation | indicator: answer withheld by validation (likely incomplete / no substantive answer) | pipeline validator codes on raw output: provision_citation_mismatch, uncited_statement, low_overlap_with_cited_source, invented_condition, condition_not_in_cited_source, repeated_statement | Q31: N | R31: 0 | S31: 0 | T31: 0 | U31: 0 | V31: 1 | X31: ANSWERABLE | Y31: unsupported | Z31: mismatched_statements_replaced+failed_repair_fallback | AA31: 21 CFR 117.10; 21 CFR 117.110(a); 21 CFR 117.126(a); 21 CFR 117.130(a); 21 CFR 117.135(a)(1); 21 CFR 117.136(a); 21 CFR 117.137; 21 CFR 117.139; 21 CFR 117.140(a); 21 CFR 117.145; 21 CFR 117.150(a); 21 CFR 117.155(a); 21 CFR 117.160(a); 21 CFR 117.165(a); 21 CFR 117.170(a); 21 CFR 117.180(a); 21 CFR 117.190(a); 21 CFR 117.1(a); 21 CFR 117.201(a); 21 CFR 117.206(a); 21 CFR 117.20(a); 21 CFR 117.251(a); 21 CFR 117.254(a) | AC31: A 'qualified facility' under Part 117 requires that the facility must implement preventive controls to ensure food safety, as appropriate to the nature of the preventive control and its role in the facility's food safety system. The modified requirements apply to a qualified facility that stores unexposed packaged food requiring time/temperature control to significantly minimize or prevent the growth of pathogens. [1] If applicable, the requirements apply to a qualified facility that stores unexposed packaged food requiring time/temperature control to significantly minimize or prevent the growth of, or toxin production by pathogens. [1] As appropriate, the preventive controls required under § 117.135 are subject to the following preventive control management components as appropriate to ensure the effectiveness of the preventive controls, taking into account the nature of the preventive control and its role in the facility's food safety system. [9] As appropriate to the nature of the preventive control and its role in the facility's food safety system, verification activities must include, as appropriate to the facility, the food, and the nature of the preventive control. [10] As appropriate to the nature of the preventive control and its role in the facility's food safety system, corrective actions and corrections must be conducted as appropriate to the nature of the hazard and the nature of the preventive control. [11] As appropriate to the nature of the preventive control and its role in the facility's food safety system, verification activities must include, as appropriate to the facility, the food, and the nature of the preventive control. [12] As appropriate to the nature of the preventive control and its role in the facility's food safety system, validation activities must include, as appropriate to the facility, the food, and the nature of the preventive control. [13] As appropriate to the nature of the preventive control and its role in the facility's food safety system, reanalysis of the food safety plan as a whole must be conducted at least once every 3 years. [15] As appropriate to the nature of the preventive control and its role in the facility's food safety system, implementation records must be established and maintained. [17] As appropriate to the nature of the preventive control and its role in the facility's food safety system, attestations to be submitted must include the following. [19] As appropriate to the nature of the preventive control and its role in the facility's food safety system, modified requirements apply to a qualified facility that is solely engaged in the storage of unexposed packaged food. [20] | AD31: unmarked | AE31: 31
A32: F-003 | B32: Human Food — 21 CFR 117 | C32: Direct Lookup | D32: Basic | E32: What CGMP requirements apply to personnel under Part 117 Subpart B? | F32: [DRAFT KEY - NOT SME-VERIFIED] Disease control, cleanliness, hand washing, jewelry, glove use, hair restraints. | G32: The CGMP requirements under Part 117 Subpart B include personnel management, defect action levels, food safety plan, hazard analysis, preventive controls, circumstances in which preventive controls are not required, assurances under preventive controls, recall plans, preventive control management components, monitoring, corrective actions and corrections, verification, validation, reanalysis, implementation records, and attestations. - 21 CFR 117.10 requires personnel management to ensure precautions are taken to reduce defects. - 21 CFR 117.110(a) mandates quality control operations to reduce defects to the lowest feasible level. - 21 CFR 117.126(a) requires a food safety plan. - 21 CFR 117.130(a) mandates a hazard analysis. - 21 CFR 117.135(a)(1) requires preventive controls to minimize or prevent hazards. - 21 CFR 117.136(a) states that preventive controls are not required if a hazard is identified and certain circumstances apply. - 21 CFR 117.137 requires written assurances to act consistently with them. - 21 CFR 117.139 mandates a recall plan for hazards requiring preventive controls. - 21 CFR 117.140(a) requires preventive control management components. - 21 CFR 117.145 mandates monitoring activities. - 21 CFR 117.150(a) requires corrective action procedures. - 21 CFR 117.155(a) mandates verification activities. - 21 CFR 117.160(a) requires validation of preventive controls. - 21 CFR 117.165(a) mandates verification of implementation and effectiveness. - 21 CFR 117.170(a) requires reanalysis every 3 years. - 21 CFR 117.180(a) requires implementation records. - 21 CFR 117.190(a) requires attestations. - 21 CFR 117.201(a) requires modified requirements for a qualified facility. - 21 CFR 117.206(a) requires temperature control activities for unexposed packaged food. - 21 CFR 117.20(a) requires grounds maintenance. - 21 CFR 117.251(a) states that FDA may withdraw an exemption. - 21 CFR 117.254(a) requires approval for withdrawal. 21 CFR 117.10 (eCFR, binding, verbatim): The management of the establishment must take reasonable measures and precautions to ensure the following: [1]. 21 CFR 117.1(a) (eCFR, binding, verbatim): (a) The criteria and definitions in this part apply in determining whether a food is: [18]. | H32: 21 CFR 117.10 | I32: Part 117, 21 CFR 117.10, 21 CFR 117.110(a), 21 CFR 117.126(a), 21 CFR 117.130(a), 21 CFR 117.135(a)(1), 21 CFR 117.136(a), 21 CFR 117.137, 21 CFR 117.139, 21 CFR 117.140(a), 21 CFR 117.145, 21 CFR 117.150(a), 21 CFR 117.155(a), 21 CFR 117.160(a), 21 CFR 117.165(a), 21 CFR 117.170(a), 21 CFR 117.180(a), 21 CFR 117.190(a), 21 CFR 117.201(a), 21 CFR 117.206(a), 21 CFR 117.20(a), 21 CFR 117.251(a), 21 CFR 117.254(a), 21 CFR 117.1(a) | J32: draft section cited | K32: 83.13 | L32: OK | M32: FAIL | O32: Names 117.10 but describes it only as 'personnel management to ensure precautions are taken to reduce defects'. None of the subpart B personnel requirements (disease control, cleanliness, hand washing, jewellery, glove use, hair restraints) appear; the answer instead lists subpart C preventive-control sections. | P32: Draft key 117.10 verified correct. The section-by-section descriptions it does give are individually accurate, so citation accuracy is met; it fails on substance and completeness. || MACHINE CHECKS: pipeline validator codes on raw output: uncited_statement, material_group_uncovered, qualifier_dropped | Q32: N | R32: 1 | S32: 0 | T32: 1 | U32: 0 | V32: 1 | X32: ANSWERABLE | Y32: valid | Z32: appended_missing_items | AA32: 21 CFR 117.10; 21 CFR 117.110(a); 21 CFR 117.126(a); 21 CFR 117.130(a); 21 CFR 117.135(a)(1); 21 CFR 117.136(a); 21 CFR 117.137; 21 CFR 117.139; 21 CFR 117.140(a); 21 CFR 117.145; 21 CFR 117.150(a); 21 CFR 117.155(a); 21 CFR 117.160(a); 21 CFR 117.165(a); 21 CFR 117.170(a); 21 CFR 117.180(a); 21 CFR 117.190(a); 21 CFR 117.1(a); 21 CFR 117.201(a); 21 CFR 117.206(a); 21 CFR 117.20(a); 21 CFR 117.251(a); 21 CFR 117.254(a) | AC32: The CGMP requirements under Part 117 Subpart B include personnel management, defect action levels, food safety plan, hazard analysis, preventive controls, circumstances in which preventive controls are not required, assurances under preventive controls, recall plans, preventive control management components, monitoring, corrective actions and corrections, verification, validation, reanalysis, implementation records, and attestations. - 21 CFR 117.10 requires personnel management to ensure precautions are taken to reduce defects. - 21 CFR 117.110(a) mandates quality control operations to reduce defects to the lowest feasible level. - 21 CFR 117.126(a) requires a food safety plan. - 21 CFR 117.130(a) mandates a hazard analysis. - 21 CFR 117.135(a)(1) requires preventive controls to minimize or prevent hazards. - 21 CFR 117.136(a) states that preventive controls are not required if a hazard is identified and certain circumstances apply. - 21 CFR 117.137 requires written assurances to act consistently with them. - 21 CFR 117.139 mandates a recall plan for hazards requiring preventive controls. - 21 CFR 117.140(a) requires preventive control management components. - 21 CFR 117.145 mandates monitoring activities. - 21 CFR 117.150(a) requires corrective action procedures. - 21 CFR 117.155(a) mandates verification activities. - 21 CFR 117.160(a) requires validation of preventive controls. - 21 CFR 117.165(a) mandates verification of implementation and effectiveness. - 21 CFR 117.170(a) requires reanalysis every 3 years. - 21 CFR 117.180(a) requires implementation records. - 21 CFR 117.190(a) requires attestations. - 21 CFR 117.201(a) requires modified requirements for a qualified facility. - 21 CFR 117.206(a) requires temperature control activities for unexposed packaged food. - 21 CFR 117.20(a) requires grounds maintenance. - 21 CFR 117.251(a) states that FDA may withdraw an exemption. - 21 CFR 117.254(a) requires approval for withdrawal. | AD32: unmarked | AE32: 32
A33: F-004 | B33: Human Food — 21 CFR 117 | C33: Direct Lookup | D33: Intermediate | E33: What sanitation requirements apply to plant and grounds under Part 117 Subpart B? | F33: [DRAFT KEY - NOT SME-VERIFIED] Grounds maintenance, plant construction and design, sanitary operations, cleaning and sanitizing, pest control. | G33: Under Part 117 Subpart B, sanitation requirements apply to plant and grounds. The requirements include ensuring the grounds are kept in a condition that protects against contamination of food, with methods for adequate maintenance. The grounds must be maintained in a condition that will protect against the contamination of food, and the methods for adequate maintenance must include [1]. The available regulatory sources do not provide enough information to answer this question. | H33: 21 CFR 117.20; 117.35 | I33: Part 117, 21 CFR 117.10 | J33: same part, different section | K33: 12.49 | L33: OK | M33: FAIL | O33: The grounds-protection statement is substantively right but cited to 117.10 (personnel) instead of 117.20(a), 117.35 sanitary operations is omitted entirely, and the answer then declares the sources insufficient. | P33: Draft key 117.20/117.35 verified correct against the snapshot. || MACHINE CHECKS: indicator: citation vs draft key: same part, different section | pipeline validator codes on raw output: low_overlap_with_cited_source | Q33: N | R33: 0 | S33: 0 | T33: 1 | U33: 0 | V33: 1 | X33: ANSWERABLE | Y33: valid | AA33: 21 CFR 117.10; 21 CFR 117.110(a); 21 CFR 117.126(a); 21 CFR 117.130(a); 21 CFR 117.135(a)(1); 21 CFR 117.136(a); 21 CFR 117.137; 21 CFR 117.139; 21 CFR 117.140(a); 21 CFR 117.145; 21 CFR 117.150(a); 21 CFR 117.155(a); 21 CFR 117.160(a); 21 CFR 117.165(a); 21 CFR 117.170(a); 21 CFR 117.180(a); 21 CFR 117.190(a); 21 CFR 117.1(a); 21 CFR 117.201(a); 21 CFR 117.206(a); 21 CFR 117.20(a); 21 CFR 117.251(a); 21 CFR 117.254(a) | AC33: Under Part 117 Subpart B, sanitation requirements apply to plant and grounds. The requirements include ensuring the grounds are kept in a condition that protects against contamination of food, with methods for adequate maintenance. The grounds must be maintained in a condition that will protect against the contamination of food, and the methods for adequate maintenance must include [1]. The available regulatory sources do not provide enough information to answer this question. | AD33: unmarked | AE33: 33
A34: F-005 | B34: Human Food — 21 CFR 117 | C34: Direct Lookup | D34: Intermediate | E34: What requirements apply to equipment and utensils under Part 117 Subpart B? | F34: [DRAFT KEY - NOT SME-VERIFIED] Design, materials, workmanship, seams, temperature-measuring devices, compressed air and gases. | G34: Under Part 117 Subpart B, the requirements apply to equipment and utensils. The following requirements apply: - 21 CFR 117.10: The management of the establishment must take reasonable measures and precautions to ensure the following: [1] - 21 CFR 117.110(a): The manufacturer, processor, packer, and holder of food must at all times utilize quality control operations that reduce natural or unavoidable defects to the lowest level currently feasible [2]. - 21 CFR 117.126(a): Requirement for a food safety plan [3]. - 21 CFR 117.130(a): Requirement for a hazard analysis [4]. - 21 CFR 117.135(a)(1): You must identify and implement preventive controls to provide assurances that any hazards requiring a preventive control will be significantly minimized or prevented and the food manufactured, processed, packed, or held by your facility will not be adulterated under section 402 of the Federal Food, Drug, and Cosmetic Act or misbranded under section 403(w) of the Federal Food, Drug, and Cosmetic Act [5]. - 21 CFR 117.136(a): Circumstances. 21 CFR 117.139 (eCFR, binding, verbatim): For food with a hazard requiring a preventive control: [8]. 21 CFR 117.170(a) (eCFR, binding, verbatim): (a) You must conduct a reanalysis of the food safety plan as a whole at least once every 3 years; [15]. 21 CFR 117.180(a) (eCFR, binding, verbatim): (a) One or more preventive controls qualified individuals must do or oversee the following: [16]. 21 CFR 117.190(a) (eCFR, binding, verbatim): (a) You must establish and maintain the following records documenting implementation of the food safety plan: [17]. 21 CFR 117.1(a) (eCFR, binding, verbatim): (a) The criteria and definitions in this part apply in determining whether a food is: [18]. 21 CFR 117.201(a) (eCFR, binding, verbatim): (a) Attestations to be submitted. A qualified facility must submit the following attestations to FDA: [19]. 21 CFR 117.206(a) (eCFR, binding, verbatim): (a) If a facility that is solely engaged in the storage of unexposed packaged food stores any such refrigerated packaged food that requires time/temperature control to significantly minimize or prevent the growth of, or toxin production by pathogens, the facility must conduct the following activities as appropriate to ensure the effectiveness of the temperature controls: [20]. 21 CFR 117.20(a) (eCFR, binding, verbatim): (a) Grounds. The grounds about a food plant under the control of the operator must be kept in a condition that will protect against the contamination of food. The methods for adequate maintenance of grounds must include: [21]. 21 CFR 117.251(a) (eCFR, binding, verbatim): (a) FDA may withdraw a qualified facility exemption under § 117.5(a): [22]. 21 CFR 117.254(a) (eCFR, binding, verbatim): (a) An FDA Division Director in whose division the qualified facility is located (or, in the case of a foreign facility, the Director of the Office of Compliance in the Center for Food Safety and Applied Nutrition), or an FDA official senior to either such Director, must approve an order to withdraw the exemption before the order is issued [23]. | H34: 21 CFR 117.40 | I34: Part 117, 21 CFR 117.10, 21 CFR 117.110(a), 21 CFR 117.126(a), 21 CFR 117.130(a), 21 CFR 117.135(a)(1), 21 CFR 117.136(a), 21 CFR 117.139, 21 CFR 117.170(a), 21 CFR 117.180(a), 21 CFR 117.190(a), 21 CFR 117.1(a), 21 CFR 117.201(a), 21 CFR 117.206(a), 21 CFR 117.20(a), 21 CFR 117.251(a), § 117.5(a), 21 CFR 117.254(a) | J34: same part, different section | K34: 118.68 | L34: OK | M34: FAIL | O34: Never reaches 117.40. Lists personnel, defect action level and preventive-control sections as though they were the equipment requirements; cleanability, materials, workmanship, seams and temperature-measuring devices are all absent. | P34: Draft key 117.40 verified correct against the snapshot. || MACHINE CHECKS: indicator: citation vs draft key: same part, different section | pipeline validator codes on raw output: provision_citation_mismatch, paragraph_misattribution, material_group_uncovered, qualifier_dropped | Q34: N | R34: 0 | S34: 0 | T34: 0 | U34: 0 | V34: 1 | X34: ANSWERABLE | Y34: incomplete | Z34: misattributed_statements_replaced+mismatched_statements_replaced+appended_missing_items | AA34: 21 CFR 117.10; 21 CFR 117.110(a); 21 CFR 117.126(a); 21 CFR 117.130(a); 21 CFR 117.135(a)(1); 21 CFR 117.136(a); 21 CFR 117.137; 21 CFR 117.139; 21 CFR 117.140(a); 21 CFR 117.145; 21 CFR 117.150(a); 21 CFR 117.155(a); 21 CFR 117.160(a); 21 CFR 117.165(a); 21 CFR 117.170(a); 21 CFR 117.180(a); 21 CFR 117.190(a); 21 CFR 117.1(a); 21 CFR 117.201(a); 21 CFR 117.206(a); 21 CFR 117.20(a); 21 CFR 117.251(a); 21 CFR 117.254(a) | AC34: Under Part 117 Subpart B, the requirements apply to equipment and utensils. The following requirements apply: - 21 CFR 117.10: The management of the establishment must take reasonable measures and precautions to ensure the following: [1] - 21 CFR 117.110(a): The manufacturer, processor, packer, and holder of food must at all times utilize quality control operations that reduce natural or unavoidable defects to the lowest level currently feasible. [2] - 21 CFR 117.126(a): Requirement for a food safety plan. [3] - 21 CFR 117.130(a): Requirement for a hazard analysis. [4] - 21 CFR 117.135(a)(1): You must identify and implement preventive controls to provide assurances that any hazards requiring a preventive control will be significantly minimized or prevented and the food manufactured, processed, packed, or held by your facility will not be adulterated under section 402 of the Federal Food, Drug, and Cosmetic Act or misbranded under section 403(w) of the Federal Food, Drug, and Cosmetic Act. [5] - 21 CFR 117.136(a): Circumstances. If you are a manufacturer/processor, you are not required to implement a preventive control when you identify a hazard requiring a preventive control (identified hazard) and any of the following circumstances apply: [9] - 21 CFR 117.137: A facility that provides a written assurance under § 117.136(a)(2), (3), or (4) must act consistently with the assurance and document its actions taken to satisfy the written assurance. [7] - 21 CFR 117.139: For food with a hazard requiring a preventive control: [8] - 21 CFR 117.140(a): Except as provided by paragraphs (b) and (c) of this section, the preventive controls required under § 117.135 are subject to the following preventive control management components as appropriate to ensure the effectiveness of the preventive controls, taking into account the nature of the preventive control and its role in the facility's food safety system. [9] - 21 CFR 117.145: As appropriate to the nature of the preventive control and its role in the facility's food safety system: [10] - 21 CFR 117.150(a): Corrective action procedures. As appropriate to the nature of the hazard and the nature of the preventive control, except as provided by paragraph (c) of this section: [11] - 21 CFR 117.155(a): Verification. Verification activities must include, as appropriate to the nature of the preventive control and its role in the facility's food safety system: [12] - 21 CFR 117.160(a): You must validate that the preventive controls identified and implemented in accordance with § 117.135 are adequate to control the hazard as appropriate to the nature of the preventive control and its role in the facility's food safety system. [13] | AD34: unmarked | AE34: 34
A35: F-006 | B35: Human Food — 21 CFR 117 | C35: Direct Lookup | D35: Intermediate | E35: What are the Part 117 CGMP requirements for warehousing and distribution? | F35: [DRAFT KEY - NOT SME-VERIFIED] Storage and transport under conditions protecting against contamination and deterioration. | G35: The Part 117 CGMP requirements for warehousing and distribution include the following: - 21 CFR 117.10: Personnel requirements to ensure proper management of the establishment. - 21 CFR 117.110(a): Defect action levels to reduce natural or unavoidable defects. - 21 CFR 117.126(a): A food safety plan requirement. - 21 CFR 117.130(a): A hazard analysis requirement. - 21 CFR 117.135(a)(1): Preventive controls to minimize or prevent hazards. - 21 CFR 117.136(a): Circumstances in which preventive controls are not required. - 21 CFR 117.137: Assurance requirements under preventive controls. - 21 CFR 117.139: Recall plan requirements. - 21 CFR 117.140(a): Preventive control management components. - 21 CFR 117.145: Monitoring requirements. - 21 CFR 117.150(a): Corrective action procedures. - 21 CFR 117.155(a): Verification activities. - 21 CFR 117.160(a): Validation of preventive controls. - 21 CFR 117.165(a): Verification of implementation and effectiveness. - 21 CFR 117.170(a): Reanalysis of the food safety plan. - 21 CFR 117.180(a): Implementation records for preventive controls. - 21 CFR 117.190(a): Applicability and status requirements. - 21 CFR 117.201(a): Modified requirements for a qualified facility. - 21 CFR 117.206(a): Activities for unexposed packaged food storage. 21 CFR 117.10 (eCFR, binding, verbatim): The management of the establishment must take reasonable measures and precautions to ensure the following: [1]. 21 CFR 117.1(a) (eCFR, binding, verbatim): (a) The criteria and definitions in this part apply in determining whether a food is: [18]. 21 CFR 117.20(a) (eCFR, binding, verbatim): (a) Grounds. The grounds about a food plant under the control of the operator must be kept in a condition that will protect against the contamination of food. The methods for adequate maintenance of grounds must include: [21]. 21 CFR 117.251(a) (eCFR, binding, verbatim): (a) FDA may withdraw a qualified facility exemption under § 117.5(a): [22]. 21 CFR 117.254(a) (eCFR, binding, verbatim): (a) An FDA Division Director in whose division the qualified facility is located (or, in the case of a foreign facility, the Director of the Office of Compliance in the Center for Food Safety and Applied Nutrition), or an FDA official senior to either such Director, must approve an order to withdraw the exemption before the order is issued [23]. | H35: 21 CFR 117.93 | I35: Part 117, 21 CFR 117.10, 21 CFR 117.110(a), 21 CFR 117.126(a), 21 CFR 117.130(a), 21 CFR 117.135(a)(1), 21 CFR 117.136(a), 21 CFR 117.137, 21 CFR 117.139, 21 CFR 117.140(a), 21 CFR 117.145, 21 CFR 117.150(a), 21 CFR 117.155(a), 21 CFR 117.160(a), 21 CFR 117.165(a), 21 CFR 117.170(a), 21 CFR 117.180(a), 21 CFR 117.190(a), 21 CFR 117.201(a), 21 CFR 117.206(a), 21 CFR 117.1(a), 21 CFR 117.20(a), 21 CFR 117.251(a), § 117.5(a), 21 CFR 117.254(a) | J35: same part, different section | K35: 52.18 | L35: OK | M35: FAIL | O35: Never reaches 117.93. The single requirement asked for - storage and transport under conditions protecting against contamination and deterioration - is replaced by a list of the preventive-control sections. | P35: Draft key 117.93 verified correct against the snapshot. || MACHINE CHECKS: indicator: citation vs draft key: same part, different section | pipeline validator codes on raw output: material_group_uncovered, qualifier_dropped | Q35: N | R35: 0 | S35: 0 | T35: 0 | U35: 0 | V35: 1 | X35: ANSWERABLE | Y35: valid | Z35: appended_missing_items | AA35: 21 CFR 117.10; 21 CFR 117.110(a); 21 CFR 117.126(a); 21 CFR 117.130(a); 21 CFR 117.135(a)(1); 21 CFR 117.136(a); 21 CFR 117.137; 21 CFR 117.139; 21 CFR 117.140(a); 21 CFR 117.145; 21 CFR 117.150(a); 21 CFR 117.155(a); 21 CFR 117.160(a); 21 CFR 117.165(a); 21 CFR 117.170(a); 21 CFR 117.180(a); 21 CFR 117.190(a); 21 CFR 117.1(a); 21 CFR 117.201(a); 21 CFR 117.206(a); 21 CFR 117.20(a); 21 CFR 117.251(a); 21 CFR 117.254(a) | AC35: The Part 117 CGMP requirements for warehousing and distribution include the following: - 21 CFR 117.10: Personnel requirements to ensure proper management of the establishment. - 21 CFR 117.110(a): Defect action levels to reduce natural or unavoidable defects. - 21 CFR 117.126(a): A food safety plan requirement. - 21 CFR 117.130(a): A hazard analysis requirement. - 21 CFR 117.135(a)(1): Preventive controls to minimize or prevent hazards. - 21 CFR 117.136(a): Circumstances in which preventive controls are not required. - 21 CFR 117.137: Assurance requirements under preventive controls. - 21 CFR 117.139: Recall plan requirements. - 21 CFR 117.140(a): Preventive control management components. - 21 CFR 117.145: Monitoring requirements. - 21 CFR 117.150(a): Corrective action procedures. - 21 CFR 117.155(a): Verification activities. - 21 CFR 117.160(a): Validation of preventive controls. - 21 CFR 117.165(a): Verification of implementation and effectiveness. - 21 CFR 117.170(a): Reanalysis of the food safety plan. - 21 CFR 117.180(a): Implementation records for preventive controls. - 21 CFR 117.190(a): Applicability and status requirements. - 21 CFR 117.201(a): Modified requirements for a qualified facility. - 21 CFR 117.206(a): Activities for unexposed packaged food storage. | AD35: unmarked | AE35: 35
A36: F-007 | B36: Human Food — 21 CFR 117 | C36: Direct Lookup | D36: Basic | E36: What must a food safety plan contain under Part 117? | F36: [DRAFT KEY - NOT SME-VERIFIED] Hazard analysis, preventive controls, supply-chain program, recall plan, monitoring, corrective action, verification procedures. | G36: Under Part 117, a food safety plan must contain requirements for hazard analysis and preventive controls, as appropriate to the nature of the preventive control and its role in the facility's food safety system. [1] The requirements for a food safety plan include identifying and implementing preventive controls to significantly minimize or prevent hazards, as appropriate. [13] The requirements for a hazard analysis include identifying and implementing preventive controls to provide assurances that any hazards requiring a preventive control will be significantly minimized or prevented. [14] The requirements for a preventive control management components include ensuring the effectiveness of the preventive controls, taking into account the nature of the preventive control and its role in the facility's food safety system. [19] The requirements for monitoring include conducting activities that include verification, reanalysis, and validation of the preventive controls. [15] The requirements for corrective actions and corrections include implementing procedures to address the hazards and prevent recurrence. [11] The requirements for verification include ensuring the preventive controls are consistently implemented and effectively and significantly minimizing or preventing the hazards. [16] The requirements for reanalysis include conducting a reanalysis of the food safety plan as a whole at least once every 3 years. [15] The requirements for implementation records include documenting the implementation of the food safety plan. [17] The requirements for applicability and status include determining whether a food is subject to the modified requirements. [20] The requirements for plant and grounds include maintaining the grounds in a condition that will protect against contamination. [22] The requirements for withdrawal of an exemption include approving an order to withdraw the exemption before the order is issued. [23] | H36: 21 CFR 117.126 | I36: Part 117, 21 CFR 117.10, 21 CFR 117.150(a), 21 CFR 117.160(a), 21 CFR 117.165(a), 21 CFR 117.170(a), 21 CFR 117.180(a), 21 CFR 117.190(a), 21 CFR 117.201(a), 21 CFR 117.206(a), 21 CFR 117.251(a), 21 CFR 117.254(a) | J36: same part, different section | K36: 40.16 | L36: OK | M36: FAIL | O36: Touches several plan contents (hazard analysis, preventive controls, monitoring, corrective actions, verification) but omits the written supply-chain program and recall plan, and attributes the plan-contents requirement to 117.10 and 117.160 rather than 117.126(b). | P36: Draft key 117.126 verified correct against the snapshot. || MACHINE CHECKS: indicator: citation vs draft key: same part, different section | pipeline validator codes on raw output: low_overlap_with_cited_source, condition_not_in_cited_source | Q36: N | R36: 0 | S36: 0 | T36: 1 | U36: 0 | V36: 1 | X36: ANSWERABLE | Y36: valid | AA36: 21 CFR 117.10; 21 CFR 117.110(a); 21 CFR 117.126(a); 21 CFR 117.130(a); 21 CFR 117.135(a)(1); 21 CFR 117.136(a); 21 CFR 117.137; 21 CFR 117.139; 21 CFR 117.140(a); 21 CFR 117.145; 21 CFR 117.150(a); 21 CFR 117.155(a); 21 CFR 117.160(a); 21 CFR 117.165(a); 21 CFR 117.170(a); 21 CFR 117.180(a); 21 CFR 117.190(a); 21 CFR 117.1(a); 21 CFR 117.201(a); 21 CFR 117.206(a); 21 CFR 117.20(a); 21 CFR 117.251(a); 21 CFR 117.254(a) | AC36: Under Part 117, a food safety plan must contain requirements for hazard analysis and preventive controls, as appropriate to the nature of the preventive control and its role in the facility's food safety system. [1] The requirements for a food safety plan include identifying and implementing preventive controls to significantly minimize or prevent hazards, as appropriate. [13] The requirements for a hazard analysis include identifying and implementing preventive controls to provide assurances that any hazards requiring a preventive control will be significantly minimized or prevented. [14] The requirements for a preventive control management components include ensuring the effectiveness of the preventive controls, taking into account the nature of the preventive control and its role in the facility's food safety system. [19] The requirements for monitoring include conducting activities that include verification, reanalysis, and validation of the preventive controls. [15] The requirements for corrective actions and corrections include implementing procedures to address the hazards and prevent recurrence. [11] The requirements for verification include ensuring the preventive controls are consistently implemented and effectively and significantly minimizing or preventing the hazards. [16] The requirements for reanalysis include conducting a reanalysis of the food safety plan as a whole at least once every 3 years. [15] The requirements for implementation records include documenting the implementation of the food safety plan. [17] The requirements for applicability and status include determining whether a food is subject to the modified requirements. [20] The requirements for plant and grounds include maintaining the grounds in a condition that will protect against contamination. [22] The requirements for withdrawal of an exemption include approving an order to withdraw the exemption before the order is issued. [23] | AD36: unmarked | AE36: 36
A37: F-008 | B37: Human Food — 21 CFR 117 | C37: Direct Lookup | D37: Intermediate | E37: What does the hazard analysis requirement of Part 117 require a facility to evaluate? | F37: [DRAFT KEY - NOT SME-VERIFIED] Identification of known or reasonably foreseeable biological, chemical, and physical hazards; hazard evaluation for severity and probability. | G37: The generated answer could not be validated against the retrieved regulatory evidence, so it is not shown. The retrieved sources were not verified to answer the question as asked, so their text is not quoted as an answer. Sources consulted: 21 CFR 117.10, 21 CFR 117.110(a), 21 CFR 117.126(a), 21 CFR 117.130(a), 21 CFR 117.135(a)(1) and 18 more. | H37: 21 CFR 117.130 | I37: none (answer withheld) | J37: no CFR citation | K37: 49.88 | L37: OK | M37: FAIL | O37: No answer delivered: validation withheld the draft. The biological, chemical (including radiological) and physical hazard categories and the severity/probability evaluation of 117.130(b)-(c) are never stated. | P37: Draft key 117.130 verified correct against the snapshot. || MACHINE CHECKS: indicator: citation vs draft key: no CFR citation | indicator: answer withheld by validation (likely incomplete / no substantive answer) | pipeline validator codes on raw output: degenerate_output, truncated, low_overlap_with_cited_source, synthesis_citation_gap, repeated_statement | Q37: N | R37: 0 | S37: 0 | T37: 0 | U37: 0 | V37: 1 | X37: ANSWERABLE | Y37: unsupported | Z37: unvalidated_answer_withheld | AA37: 21 CFR 117.10; 21 CFR 117.110(a); 21 CFR 117.126(a); 21 CFR 117.130(a); 21 CFR 117.135(a)(1); 21 CFR 117.136(a); 21 CFR 117.137; 21 CFR 117.139; 21 CFR 117.140(a); 21 CFR 117.145; 21 CFR 117.150(a); 21 CFR 117.155(a); 21 CFR 117.160(a); 21 CFR 117.165(a); 21 CFR 117.170(a); 21 CFR 117.180(a); 21 CFR 117.190(a); 21 CFR 117.1(a); 21 CFR 117.201(a); 21 CFR 117.206(a); 21 CFR 117.20(a); 21 CFR 117.251(a); 21 CFR 117.254(a) | AC37: The hazard analysis requirement of Part 117 requires a facility to evaluate hazards and implement preventive controls to minimize or prevent food hazards. [1] The hazard analysis requirement of Part 117 requires a facility to evaluate hazards and implement preventive controls to provide assurances that any hazards requiring a preventive control will be significantly minimized or prevented and the food manufactured, processed, packed, or held by your facility will not be adulterated under section 402 of the Federal Food, Drug, and Cosmetic Act or misbranded under section 403(w) of the Federal Food, Drug, and Cosmetic Act. [4] The hazard analysis requirement of Part 117 requires a facility to evaluate hazards and implement preventive controls to provide assurances that any hazards requiring a preventive control will be significantly minimized or prevented and the food manufactured, processed, packed, or held by your facility will not be adulterated under section 402 of the Federal Food, Drug, and Cosmetic Act or misbranded under section 403(w) of the Federal Food, Drug, and Cosmetic Act. [4] The hazard analysis requirement of Part 117 requires a facility to evaluate hazards and implement preventive controls to provide assurances that any hazards requiring a preventive control will be significantly minimized or prevented and the food manufactured, processed, packed, or held by your facility will not be adulterated under section 402 of the Federal Food, Drug, and Cosmetic Act or misbranded under section 403(w) of the Federal Food, Drug, and Cosmetic Act. [4] The hazard analysis requirement of Part 1 | AD37: unmarked | AE37: 37
A38: F-009 | B38: Human Food — 21 CFR 117 | C38: Distinction | D38: Advanced | E38: What is the difference between a process preventive control, a sanitation preventive control, and an allergen preventive control under Part 117? | F38: [DRAFT KEY - NOT SME-VERIFIED] Categories of preventive controls, written procedures, parameters and values, application to identified hazards. | G38: Under Part 117, a process preventive control is a measure implemented to prevent hazards that require a preventive control, such as contamination or microbial growth, and is subject to the requirements of § 117.135. A sanitation preventive control is a measure to prevent hazards related to sanitation, such as bacterial contamination, and is also subject to the requirements of § 117.135. An allergen preventive control is a measure to prevent allergens, such as allergens in food, and is also subject to the requirements of § 117.135. The requirements apply as appropriate to the nature of the preventive control and its role in the facility's food safety system. The preventive controls must be implemented and verified as appropriate to ensure their effectiveness. The requirements apply to the qualified individual and auditor as specified in § 117.160(a). The implementation records must be maintained as required in § 117.1(a). The applicability and status of the requirements are determined in § 117.201(a). The modified requirements apply to a qualified facility solely engaged in the storage of unexposed packaged food as specified in § 117.20(a). The requirements apply to the plant and grounds as specified in § 117.251(a). The issuance of an order to withdraw a qualified facility exemption is approved by an FDA official senior to the Division Director as specified in § 117.254(a). [1] [2] [3] [4] [5] [6] [7] [8] [9] [10] [11] [12] [13] [14] [15] [16] [17] [18] [19] [20] [21] [22] [23] | H38: 21 CFR 117.135 | I38: Part 117, § 117.135, § 117.160(a), § 117.1(a), § 117.201(a), § 117.20(a), § 117.251(a), § 117.254(a), 21 CFR 117.10, 21 CFR 117.110(a), 21 CFR 117.126(a), 21 CFR 117.130(a), 21 CFR 117.135(a)(1), 21 CFR 117.136(a), 21 CFR 117.137, 21 CFR 117.139, 21 CFR 117.140(a), 21 CFR 117.145, 21 CFR 117.150(a), 21 CFR 117.155(a), 21 CFR 117.165(a), 21 CFR 117.170(a), 21 CFR 117.180(a), 21 CFR 117.190(a), 21 CFR 117.206(a) | J38: draft section cited | K38: 44.49 | L38: OK | M38: FAIL | O38: Defines the three control types circularly ('a sanitation preventive control is a measure to prevent hazards related to sanitation') instead of giving 117.135(c): process parameters such as heat treatment and refrigeration, sanitation controls for food-contact surfaces and environmental pathogens, and allergen controls for labelling and cross-contact. Also misattributes storage requirements to 117.20(a) and implementation records to 117.1(a). | P38: Draft key 117.135 verified correct against the snapshot. || MACHINE CHECKS: pipeline validator codes on raw output: uncited_statement | Q38: N | R38: 0 | S38: 0 | T38: 1 | U38: 0 | V38: 1 | X38: ANSWERABLE | Y38: valid | AA38: 21 CFR 117.10; 21 CFR 117.110(a); 21 CFR 117.126(a); 21 CFR 117.130(a); 21 CFR 117.135(a)(1); 21 CFR 117.136(a); 21 CFR 117.137; 21 CFR 117.139; 21 CFR 117.140(a); 21 CFR 117.145; 21 CFR 117.150(a); 21 CFR 117.155(a); 21 CFR 117.160(a); 21 CFR 117.165(a); 21 CFR 117.170(a); 21 CFR 117.180(a); 21 CFR 117.190(a); 21 CFR 117.1(a); 21 CFR 117.201(a); 21 CFR 117.206(a); 21 CFR 117.20(a); 21 CFR 117.251(a); 21 CFR 117.254(a) | AC38: Under Part 117, a process preventive control is a measure implemented to prevent hazards that require a preventive control, such as contamination or microbial growth, and is subject to the requirements of § 117.135. A sanitation preventive control is a measure to prevent hazards related to sanitation, such as bacterial contamination, and is also subject to the requirements of § 117.135. An allergen preventive control is a measure to prevent allergens, such as allergens in food, and is also subject to the requirements of § 117.135. The requirements apply as appropriate to the nature of the preventive control and its role in the facility's food safety system. The preventive controls must be implemented and verified as appropriate to ensure their effectiveness. The requirements apply to the qualified individual and auditor as specified in § 117.160(a). The implementation records must be maintained as required in § 117.1(a). The applicability and status of the requirements are determined in § 117.201(a). The modified requirements apply to a qualified facility solely engaged in the storage of unexposed packaged food as specified in § 117.20(a). The requirements apply to the plant and grounds as specified in § 117.251(a). The issuance of an order to withdraw a qualified facility exemption is approved by an FDA official senior to the Division Director as specified in § 117.254(a). [1] [2] [3] [4] [5] [6] [7] [8] [9] [10] [11] [12] [13] [14] [15] [16] [17] [18] [19] [20] [21] [22] [23] | AD38: unmarked | AE38: 38
A39: F-010 | B39: Human Food — 21 CFR 117 | C39: Direct Lookup | D39: Intermediate | E39: What are the monitoring requirements for preventive controls under Part 117? | F39: [DRAFT KEY - NOT SME-VERIFIED] Written procedures, monitoring as appropriate to the control, documentation in records. | G39: The monitoring requirements for preventive controls under Part 117 are specified in [15]. Preventive controls must be implemented and verified as appropriate to the nature of the control and its role in the facility's food safety system, as required by [13]. Corrective actions and corrections must be conducted as appropriate to the nature of the hazard and the preventive control, as required by [11]. Verification activities must include the following, as appropriate to the facility, the food, and the nature of the preventive control and its role in the facility's food safety system, as required by [12]. Reanalysis of the food safety plan must be conducted at least once every 3 years, as required by [15]. Implementation records must be maintained, as required by [17]. The applicability and status of the requirements must be determined, as required by [19]. The modified requirements apply to a qualified facility, as required by [20]. The grounds about a food plant must be kept in a condition that will protect against contamination, as required by [21]. The withdrawal of a qualified facility exemption must be approved by an FDA official senior to the Director, as required by [22]. The issuance of an order to withdraw the exemption must be approved by an FDA Division Director, as required by [23]. | H39: 21 CFR 117.145 | I39: Part 117, 21 CFR 117.150(a), 21 CFR 117.155(a), 21 CFR 117.160(a), 21 CFR 117.170(a), 21 CFR 117.190(a), 21 CFR 117.201(a), 21 CFR 117.206(a), 21 CFR 117.20(a), 21 CFR 117.251(a), 21 CFR 117.254(a) | J39: same part, different section | K39: 29.07 | L39: OK | M39: FAIL | O39: Says the monitoring requirements are 'specified in [15]', which is 117.170 (reanalysis), not 117.145. The written monitoring procedures, the adequate-frequency requirement and the records duty are never stated. | P39: Draft key 117.145 verified correct against the snapshot. || MACHINE CHECKS: indicator: citation vs draft key: same part, different section | pipeline validator codes on raw output: low_overlap_with_cited_source | Q39: N | R39: 0 | S39: 0 | T39: 0 | U39: 0 | V39: 1 | X39: ANSWERABLE | Y39: valid | AA39: 21 CFR 117.10; 21 CFR 117.110(a); 21 CFR 117.126(a); 21 CFR 117.130(a); 21 CFR 117.135(a)(1); 21 CFR 117.136(a); 21 CFR 117.137; 21 CFR 117.139; 21 CFR 117.140(a); 21 CFR 117.145; 21 CFR 117.150(a); 21 CFR 117.155(a); 21 CFR 117.160(a); 21 CFR 117.165(a); 21 CFR 117.170(a); 21 CFR 117.180(a); 21 CFR 117.190(a); 21 CFR 117.1(a); 21 CFR 117.201(a); 21 CFR 117.206(a); 21 CFR 117.20(a); 21 CFR 117.251(a); 21 CFR 117.254(a) | AC39: The monitoring requirements for preventive controls under Part 117 are specified in [15]. Preventive controls must be implemented and verified as appropriate to the nature of the control and its role in the facility's food safety system, as required by [13]. Corrective actions and corrections must be conducted as appropriate to the nature of the hazard and the preventive control, as required by [11]. Verification activities must include the following, as appropriate to the facility, the food, and the nature of the preventive control and its role in the facility's food safety system, as required by [12]. Reanalysis of the food safety plan must be conducted at least once every 3 years, as required by [15]. Implementation records must be maintained, as required by [17]. The applicability and status of the requirements must be determined, as required by [19]. The modified requirements apply to a qualified facility, as required by [20]. The grounds about a food plant must be kept in a condition that will protect against contamination, as required by [21]. The withdrawal of a qualified facility exemption must be approved by an FDA official senior to the Director, as required by [22]. The issuance of an order to withdraw the exemption must be approved by an FDA Division Director, as required by [23]. | AD39: unmarked | AE39: 39
A40: F-011 | B40: Human Food — 21 CFR 117 | C40: Application | D40: Advanced | E40: A metal detector fails mid-shift at a food facility. What does Part 117 require regarding corrective actions and corrections? | F40: [DRAFT KEY - NOT SME-VERIFIED] Corrective action procedures, identify and correct, evaluate affected food, prevent recurrence, distinguish corrections from corrective actions, records. | G40: The generated answer could not be validated against the retrieved regulatory evidence, so it is not shown. The retrieved sources were not verified to answer the question as asked, so their text is not quoted as an answer. Sources consulted: 21 CFR 117.10, 21 CFR 117.110(a), 21 CFR 117.126(a), 21 CFR 117.130(a), 21 CFR 117.135(a)(1) and 18 more. | H40: 21 CFR 117.150 | I40: none (answer withheld) | J40: no CFR citation | K40: 236.74 | L40: OK | M40: FAIL | O40: No answer delivered: validation withheld a truncated draft. Nothing is said about identifying and correcting the problem, evaluating the affected food, preventing recurrence, or the corrections-versus-corrective-actions distinction in 117.150. | P40: Draft key 117.150 verified correct against the snapshot. || MACHINE CHECKS: indicator: citation vs draft key: no CFR citation | indicator: answer withheld by validation (likely incomplete / no substantive answer) | pipeline validator codes on raw output: truncated, low_overlap_with_cited_source, invented_condition, condition_not_in_cited_source | Q40: N | R40: 0 | S40: 0 | T40: 0 | U40: 0 | V40: 1 | X40: ANSWERABLE | Y40: unsupported | Z40: truncation_noted+failed_repair_fallback | AA40: 21 CFR 117.10; 21 CFR 117.110(a); 21 CFR 117.126(a); 21 CFR 117.130(a); 21 CFR 117.135(a)(1); 21 CFR 117.136(a); 21 CFR 117.137; 21 CFR 117.139; 21 CFR 117.140(a); 21 CFR 117.145; 21 CFR 117.150(a); 21 CFR 117.155(a); 21 CFR 117.160(a); 21 CFR 117.165(a); 21 CFR 117.170(a); 21 CFR 117.180(a); 21 CFR 117.190(a); 21 CFR 117.1(a); 21 CFR 117.201(a); 21 CFR 117.206(a); 21 CFR 117.20(a); 21 CFR 117.251(a); 21 CFR 117.254(a) | AC40: Part 117 requires corrective actions and corrections to address a metal detector failure mid-shift at a food facility. [1] If applicable, "as appropriate" [9] must be followed. [11] Corrective action procedures must be implemented as appropriate to the nature of the hazard and the preventive control. [15] Reanalysis of the food safety plan must be conducted at least once every 3 years. [18] Implementation records must be maintained. [17] The requirements apply to a qualified facility. [20] If a facility stores unexposed packaged food requiring temperature control, temperature controls must be validated. [13] Verification activities must include validation of the preventive controls. [14] Verification of implementation and effectiveness must be conducted. [16] One or more preventive controls qualified individuals must do or oversee the implementation. [19] Attestations must be submitted. [20] The requirements apply to a facility solely engaged in the storage of unexposed packaged food. [22] Grounds must be maintained in a condition that protects against contamination. [23] An order to withdraw a qualified facility exemption must be approved. [21] Grounds must be kept in a condition that protects against contamination. [251(a)] [206(a)] [117.20(a)] [117.251(a)] [117.254(a)] [117.251(a)] [117.20(a)] [117.251(a)] [117.20(a)] [117.251(a)] [117.20(a)] [117.251(a)] [117.20(a)] [117.251(a)] [117.20(a)] [117.251(a)] [117.20(a)] [117.251(a)] [117.20(a)] [117.251(a)] [117.20(a)] [117.251(a)] [117.20(a)] [117.251(a)] [117.20(a)] [117.251(a)] [117.20(a)] [117.251(a)] [117.20(a)] [117.251(a)] [117.20(a)] [117.251(a)] [117.20(a)] [117.251(a)] [117.20(a)] [117.251(a)] [117.20(a)] [117.251(a)] [117.20(a)] [117.251(a)] [117.20(a)] [117.251(a)] [117.20(a)] [117.251(a)] [117.20(a)] [117.251(a)] [117.20(a)] [117.251(a)] [117.20(a)] [117.251(a)] [117.20(a)] [117.251(a)] [117.20(a)] [117.251(a)] [117.20(a)] [117.251(a)] [117.20(a)] [117.251(a)] [117.20(a)] [117.251(a)] [117.20(a)] [117.251(a)] [117.20(a)] [117.251(a)] [117.20(a)] [117.251(a)] [117.20(a)] [117.251(a)] [117.20(a)] [117.251(a)] [117.20(a)] [117.251(a)] [117.20(a)] [117.251(a)] [117.20(a)] [117.251(a)] [117.20(a)] [117.251(a)] [117.20(a)] [117.251(a)] [117.20(a)] [117.251(a)] [117.20(a)] [117.251(a)] [117.20(a)] [117.251(a)] [117.20(a)] [117.251(a)] [117.20(a)] [117.251(a)] [117.20(a)] [117.251(a)] [117.20(a)] [117.251(a)] [117.20(a)] [117.251(a)] [117.20(a)] [117.251(a)] [117.20(a)] [117.251(a)] [117.20(a)] [117.251(a)] [117.20(a)] [117.251(a)] [117.20(a)] [117.251(a)] [117.20(a)] [117.251(a)] [117.20(a)] [117.251(a)] [117.20(a)] [117.251(a)] [117.20(a)] [117.251(a)] [117.20(a)] [117.251(a)] [117.20(a)] [117.251(a)] [117.20(a)] [117.251(a)] [117.20(a)] [117.251(a)] [117.20(a)] [117.251(a)] [117.20(a)] [117.251(a)] [117.20(a)] [117.251(a)] [117.20(a)] [117.251(a)] [117.20(a)] [117.251(a)] [117.20(a)] [117.251(a)] [117.20(a)] [117.251(a)] [117.20(a)] [117.251(a)] [117.20(a)] [117.251(a)] [117.20(a)] [117.251(a)] [117.20(a)] [117.251(a)] [117.20(a)] [117.251(a)] [117.20(a)] [117.251(a)] [117.20(a)] [117.251(a)] [117.20(a)] [117.251(a | AD40: unmarked | AE40: 40
A41: F-012 | B41: Human Food — 21 CFR 117 | C41: Direct Lookup | D41: Intermediate | E41: What verification activities does Part 117 require? | F41: [DRAFT KEY - NOT SME-VERIFIED] Validation, verification of monitoring and corrective actions, calibration, product testing, environmental monitoring, reanalysis, records review. | G41: Part 117 requires verification activities that include, as appropriate to the nature of the preventive control and its role in the facility's food safety system, [12]. Part 117 also requires validation that the preventive controls are effectively and significantly minimizing or preventing the hazards, as appropriate to the facility, the food, and the nature of the preventive control and its role in the facility's food safety system, [13]. Part 117 requires corrective actions and corrections, as appropriate to the nature of the hazard and the nature of the preventive control, except as provided by paragraph (c) of this section, [15]. Part 117 requires verification activities, as appropriate to the nature of the preventive control and its role in the facility's food safety system, [12]. Part 117 requires reanalysis of the food safety plan as a whole at least once every 3 years, [15]. Part 117 requires implementation records documenting the implementation of the food safety plan, [17]. Part 117 requires attestations to be submitted, [20]. Part 117 requires activities to ensure the effectiveness of the temperature controls, [22]. Part 117 requires a qualified facility to maintain grounds in a condition that will protect against contamination, [21]. Part 117 requires FDA to approve an order to withdraw a qualified facility exemption, [23]. | H41: 21 CFR 117.155; 117.160 | I41: Part 117, 21 CFR 117.155(a), 21 CFR 117.160(a), 21 CFR 117.170(a), 21 CFR 117.190(a), 21 CFR 117.206(a), 21 CFR 117.20(a), 21 CFR 117.251(a), 21 CFR 117.254(a) | J41: draft section cited | K41: 31.7 | L41: OK | M41: FAIL | O41: Opens with a correct lead-in cited to 117.155(a) and mentions validation and the 3-year reanalysis, but never enumerates the five verification activities, and attributes corrective actions to 117.170 and attestations to 117.206 instead of 117.150 and 117.201. | P41: Draft key 117.155/117.160 verified correct against the snapshot. || MACHINE CHECKS: pipeline validator codes on raw output: low_overlap_with_cited_source, condition_not_in_cited_source, repeated_statement | Q41: N | R41: 0 | S41: 0 | T41: 1 | U41: 0 | V41: 1 | X41: ANSWERABLE | Y41: valid | AA41: 21 CFR 117.10; 21 CFR 117.110(a); 21 CFR 117.126(a); 21 CFR 117.130(a); 21 CFR 117.135(a)(1); 21 CFR 117.136(a); 21 CFR 117.137; 21 CFR 117.139; 21 CFR 117.140(a); 21 CFR 117.145; 21 CFR 117.150(a); 21 CFR 117.155(a); 21 CFR 117.160(a); 21 CFR 117.165(a); 21 CFR 117.170(a); 21 CFR 117.180(a); 21 CFR 117.190(a); 21 CFR 117.1(a); 21 CFR 117.201(a); 21 CFR 117.206(a); 21 CFR 117.20(a); 21 CFR 117.251(a); 21 CFR 117.254(a) | AC41: Part 117 requires verification activities that include, as appropriate to the nature of the preventive control and its role in the facility's food safety system, [12]. Part 117 also requires validation that the preventive controls are effectively and significantly minimizing or preventing the hazards, as appropriate to the facility, the food, and the nature of the preventive control and its role in the facility's food safety system, [13]. Part 117 requires corrective actions and corrections, as appropriate to the nature of the hazard and the nature of the preventive control, except as provided by paragraph (c) of this section, [15]. Part 117 requires verification activities, as appropriate to the nature of the preventive control and its role in the facility's food safety system, [12]. Part 117 requires reanalysis of the food safety plan as a whole at least once every 3 years, [15]. Part 117 requires implementation records documenting the implementation of the food safety plan, [17]. Part 117 requires attestations to be submitted, [20]. Part 117 requires activities to ensure the effectiveness of the temperature controls, [22]. Part 117 requires a qualified facility to maintain grounds in a condition that will protect against contamination, [21]. Part 117 requires FDA to approve an order to withdraw a qualified facility exemption, [23]. | AD41: unmarked | AE41: 41
A42: F-013 | B42: Human Food — 21 CFR 117 | C42: Direct Lookup | D42: Intermediate | E42: When must a facility reanalyze its food safety plan under Part 117? | F42: [DRAFT KEY - NOT SME-VERIFIED] At least every three years, and when a significant change, new hazard, unanticipated food safety problem, or ineffective control is found. | G42: The generated answer could not be validated against the retrieved regulatory evidence, so it is not shown. The retrieved sources were not verified to answer the question as asked, so their text is not quoted as an answer. Sources consulted: 21 CFR 117.10, 21 CFR 117.110(a), 21 CFR 117.126(a), 21 CFR 117.130(a), 21 CFR 117.135(a)(1) and 18 more. | H42: 21 CFR 117.170 | I42: none (answer withheld) | J42: no CFR citation | K42: 27.66 | L42: OK | M42: FAIL | O42: No answer delivered: validation withheld the draft. Neither the 3-year cycle nor the event triggers of 117.170(b) reach the user. | P42: Draft key 117.170 verified correct. The withheld draft did contain the 3-year figure, so the loss is in generation control, not retrieval. || MACHINE CHECKS: indicator: citation vs draft key: no CFR citation | indicator: answer withheld by validation (likely incomplete / no substantive answer) | pipeline validator codes on raw output: degenerate_output, truncated, low_overlap_with_cited_source, condition_not_in_cited_source, repeated_statement | Q42: N | R42: 0 | S42: 0 | T42: 0 | U42: 0 | V42: 1 | X42: ANSWERABLE | Y42: unsupported | Z42: unvalidated_answer_withheld | AA42: 21 CFR 117.10; 21 CFR 117.110(a); 21 CFR 117.126(a); 21 CFR 117.130(a); 21 CFR 117.135(a)(1); 21 CFR 117.136(a); 21 CFR 117.137; 21 CFR 117.139; 21 CFR 117.140(a); 21 CFR 117.145; 21 CFR 117.150(a); 21 CFR 117.155(a); 21 CFR 117.160(a); 21 CFR 117.165(a); 21 CFR 117.170(a); 21 CFR 117.180(a); 21 CFR 117.190(a); 21 CFR 117.1(a); 21 CFR 117.201(a); 21 CFR 117.206(a); 21 CFR 117.20(a); 21 CFR 117.251(a); 21 CFR 117.254(a) | AC42: The facility must reanalyze its food safety plan under Part 117 as appropriate [15]. The facility must conduct a reanalysis of the food safety plan as a whole at least once every 3 years [15]. The facility must establish and maintain records documenting implementation of the food safety plan [17]. The facility must conduct activities that include verification of implementation and effectiveness of the preventive controls [14]. The facility must validate that the preventive controls are effectively and significantly minimizing or preventing the hazards [13]. The facility must identify and implement preventive controls to provide assurances that any hazards requiring a preventive control will be significantly minimized or prevented [5]. The facility must ensure that the preventive controls are implemented and consistently managed [19]. The facility must ensure that the food safety plan is properly documented and maintained [17]. The facility must ensure that the preventive controls are effectively and significantly minimizing or preventing the hazards [13]. The facility must ensure that the food safety plan is properly documented and maintained [17]. The facility must ensure that the preventive controls are effectively and significantly minimizing or preventing the hazards [13]. The facility must ensure that the food safety plan is properly documented and maintained [17]. The facility must ensure that the preventive controls are effectively | AD42: unmarked | AE42: 42
A43: F-014 | B43: Human Food — 21 CFR 117 | C43: Direct Lookup | D43: Basic | E43: What are the recall plan requirements under Part 117? | F43: [DRAFT KEY - NOT SME-VERIFIED] Written recall plan for foods with a hazard requiring a preventive control, notification, effectiveness checks, disposition. | G43: The generated answer could not be validated against the retrieved regulatory evidence, so it is not shown. The retrieved sources were not verified to answer the question as asked, so their text is not quoted as an answer. Sources consulted: 21 CFR 117.10, 21 CFR 117.110(a), 21 CFR 117.126(a), 21 CFR 117.130(a), 21 CFR 117.135(a)(1) and 18 more. | H43: 21 CFR 117.139 | I43: none (answer withheld) | J43: no CFR citation | K43: 24.63 | L43: OK | M43: FAIL | O43: No answer delivered: validation withheld the draft. The written recall plan and its four required procedures (consignee notification, public notification, effectiveness checks, disposition) are never stated. | P43: Draft key 117.139 verified correct against the snapshot. || MACHINE CHECKS: indicator: citation vs draft key: no CFR citation | indicator: answer withheld by validation (likely incomplete / no substantive answer) | pipeline validator codes on raw output: degenerate_output, truncated, low_overlap_with_cited_source, condition_not_in_cited_source, repeated_statement | Q43: N | R43: 0 | S43: 0 | T43: 0 | U43: 0 | V43: 1 | X43: ANSWERABLE | Y43: unsupported | Z43: unvalidated_answer_withheld | AA43: 21 CFR 117.10; 21 CFR 117.110(a); 21 CFR 117.126(a); 21 CFR 117.130(a); 21 CFR 117.135(a)(1); 21 CFR 117.136(a); 21 CFR 117.137; 21 CFR 117.139; 21 CFR 117.140(a); 21 CFR 117.145; 21 CFR 117.150(a); 21 CFR 117.155(a); 21 CFR 117.160(a); 21 CFR 117.165(a); 21 CFR 117.170(a); 21 CFR 117.180(a); 21 CFR 117.190(a); 21 CFR 117.1(a); 21 CFR 117.201(a); 21 CFR 117.206(a); 21 CFR 117.20(a); 21 CFR 117.251(a); 21 CFR 117.254(a) | AC43: Under Part 117, recall plan requirements are outlined in [8]. For food with a hazard requiring a preventive control, the facility must establish and maintain records documenting implementation of the food safety plan, as appropriate to the nature of the preventive control and its role in the facility's food safety system, and conduct activities that include verification, reanalysis, and validation of the preventive controls. [17] The requirements applicable to a preventive controls qualified individual and a qualified auditor are outlined in [16]. The applicability and status of a qualified facility are determined in [18]. The modified requirements that apply to a qualified facility are outlined in [20]. The requirements applicable to a preventive controls qualified individual and a qualified auditor are outlined in [16]. The applicability and status of a qualified facility are determined in [18]. The requirements applicable to a preventive controls qualified individual and a qualified auditor are outlined in [16]. The applicability and status of a qualified facility are determined in [18 | AD43: unmarked | AE43: 43
A44: F-015 | B44: Human Food — 21 CFR 117 | C44: Direct Lookup | D44: Intermediate | E44: Who is a preventive controls qualified individual and what must that person do? | F44: [DRAFT KEY - NOT SME-VERIFIED] PCQI definition, required training or job experience, preparation of the food safety plan, validation, records review. | G44: A preventive controls qualified individual (PCQI) must develop or oversee the development of the Food Safety Plan (FSP) [1]. The PCQI must have education, training, or experience (or a combination) to develop and apply a food safety system [2]. All applicable training in the development and application of risk-based preventive controls must be documented in records, including the date of the training, the type of training, and the person(s) trained [4][3]. | H44: 21 CFR 117.180; 117.3 | I44: 21 CFR 117.180(d), 21 CFR 507.53(d) | J44: draft section cited | K44: 10.03 | L44: OK | M44: FAIL | O44: Correctly says the qualified individual prepares or oversees the food safety plan and needs training or job experience, but cites a draft guidance for the first point and 21 CFR 507.53(d) - the animal-food parallel - for the training-records point, and omits validation, records review and reanalysis duties under 117.180(a). | P44: Draft key 117.180/117.3 verified correct. Cross-citing the Part 507 animal-food twin of a Part 117 requirement is a citation failure under rubric L. || MACHINE CHECKS: no machine indicators | Q44: N | R44: 0 | S44: 0 | T44: 1 | U44: 1 | V44: 1 | X44: UNKNOWN | Y44: valid | AA44: FDA Guidance: Draft Guidance for Industry: Hazard Analysis and Risk-Based Preventive Controls for Human Food (draft, 2024-01-30, Docket FDA-2016-D-2343); 21 CFR 117.180(d); 21 CFR 507.53(d); FDA Guidance: Guidance for Industry: Foreign Supplier Verification Programs for Importers of Food for Humans and Animals (final, 2023-01-10, Docket FDA-2017-D-5225) | AC44: A preventive controls qualified individual (PCQI) must develop or oversee the development of the Food Safety Plan (FSP) [1]. The PCQI must have education, training, or experience (or a combination) to develop and apply a food safety system [2]. All applicable training in the development and application of risk-based preventive controls must be documented in records, including the date of the training, the type of training, and the person(s) trained [4][3]. | AD44: unmarked | AE44: 44
A45: F-016 | B45: Human Food — 21 CFR 117 | C45: Direct Lookup | D45: Intermediate | E45: What modified requirements apply to a qualified facility under Part 117 Subpart D? | F45: [DRAFT KEY - NOT SME-VERIFIED] Attestation submissions to FDA, either hazard-control attestation or compliance-with-state-law attestation, records. | G45: The modified requirements apply to a qualified facility under Part 117 Subpart D, as appropriate [1]. The facility must conduct verification activities as appropriate to the nature of the preventive control and its role in the food safety system [14]. The requirements also include conducting a reanalysis of the food safety plan as a whole at least once every 3 years [15]. The facility must establish and maintain records documenting the implementation of the food safety plan [17]. The requirements also include conducting activities to verify the effectiveness of the preventive controls [14]. The facility must ensure that the preventive controls are implemented and effectively minimized or prevented [13]. The requirements apply to a qualified facility solely engaged in the storage of unexposed packaged food [20]. The requirements also include conducting activities to ensure the effectiveness of temperature controls [20]. The requirements apply to a qualified facility under Part 117 Subpart D [1]. | H45: 21 CFR 117.201 | I45: Part 117, 21 CFR 117.10, 21 CFR 117.160(a), 21 CFR 117.165(a), 21 CFR 117.170(a), 21 CFR 117.190(a), 21 CFR 117.206(a) | J45: same part, different section | K45: 31.7 | L45: OK | M45: FAIL | O45: Circular restatement of the question citing 117.10, 117.160, 117.165 and 117.206. The attestations a qualified facility must submit under 117.201(a) - the qualified-facility attestation and either the hazard-control or the state-law compliance attestation - are absent. | P45: Draft key 117.201 verified correct against the snapshot. || MACHINE CHECKS: indicator: citation vs draft key: same part, different section | pipeline validator codes on raw output: low_overlap_with_cited_source, condition_not_in_cited_source, invented_condition | Q45: N | R45: 0 | S45: 0 | T45: 0 | U45: 0 | V45: 1 | X45: ANSWERABLE | Y45: valid | Z45: invented_conditions_removed | AA45: 21 CFR 117.10; 21 CFR 117.110(a); 21 CFR 117.126(a); 21 CFR 117.130(a); 21 CFR 117.135(a)(1); 21 CFR 117.136(a); 21 CFR 117.137; 21 CFR 117.139; 21 CFR 117.140(a); 21 CFR 117.145; 21 CFR 117.150(a); 21 CFR 117.155(a); 21 CFR 117.160(a); 21 CFR 117.165(a); 21 CFR 117.170(a); 21 CFR 117.180(a); 21 CFR 117.190(a); 21 CFR 117.1(a); 21 CFR 117.201(a); 21 CFR 117.206(a); 21 CFR 117.20(a); 21 CFR 117.251(a); 21 CFR 117.254(a) | AC45: The modified requirements apply to a qualified facility under Part 117 Subpart D, as appropriate [1]. If applicable, the requirements must ensure the effectiveness of preventive controls, including identifying and implementing them as appropriate [13]. The facility must conduct verification activities as appropriate to the nature of the preventive control and its role in the food safety system [14]. The requirements also include conducting a reanalysis of the food safety plan as a whole at least once every 3 years [15]. The facility must establish and maintain records documenting the implementation of the food safety plan [17]. The requirements also include conducting activities to verify the effectiveness of the preventive controls [14]. The facility must ensure that the preventive controls are implemented and effectively minimized or prevented [13]. The requirements apply to a qualified facility solely engaged in the storage of unexposed packaged food [20]. The requirements also include conducting activities to ensure the effectiveness of temperature controls [20]. The requirements apply to a qualified facility under Part 117 Subpart D [1]. | AD45: unmarked | AE45: 45
A46: F-017 | B46: Human Food — 21 CFR 117 | C46: Direct Lookup | D46: Advanced | E46: What requirements apply to the storage of unexposed packaged food that requires time/temperature control under Part 117 Subpart D? | F46: [DRAFT KEY - NOT SME-VERIFIED] Temperature controls, monitoring, corrective actions, verification, records for refrigerated packaged food. | G46: The requirements apply to the storage of unexposed packaged food that requires time/temperature control under Part 117 Subpart D. [1] The establishment must take reasonable measures and precautions to ensure the following: "as appropriate" [9]; "as appropriate" [10]; "as appropriate" [11]; "as appropriate" [12]; "as appropriate" [13]; "as appropriate" [14]; "as appropriate" [20]. [1] | H46: 21 CFR 117.206 | I46: Part 117, 21 CFR 117.10, 21 CFR 117.140(a), 21 CFR 117.145, 21 CFR 117.150(a), 21 CFR 117.155(a), 21 CFR 117.160(a), 21 CFR 117.165(a), 21 CFR 117.206(a) | J46: draft section cited | K46: 13.34 | L46: OK | M46: FAIL | O46: Degenerate output: the phrase 'as appropriate' repeated seven times with citation markers and no content. None of 117.206(a)'s temperature controls, monitoring, corrective actions, verification or records requirements are stated. | P46: Draft key 117.206 verified correct against the snapshot. || MACHINE CHECKS: pipeline validator codes on raw output: low_overlap_with_cited_source | Q46: N | R46: 0 | S46: 0 | T46: 0 | U46: 0 | V46: 1 | X46: ANSWERABLE | Y46: valid | AA46: 21 CFR 117.10; 21 CFR 117.110(a); 21 CFR 117.126(a); 21 CFR 117.130(a); 21 CFR 117.135(a)(1); 21 CFR 117.136(a); 21 CFR 117.137; 21 CFR 117.139; 21 CFR 117.140(a); 21 CFR 117.145; 21 CFR 117.150(a); 21 CFR 117.155(a); 21 CFR 117.160(a); 21 CFR 117.165(a); 21 CFR 117.170(a); 21 CFR 117.180(a); 21 CFR 117.190(a); 21 CFR 117.1(a); 21 CFR 117.201(a); 21 CFR 117.206(a); 21 CFR 117.20(a); 21 CFR 117.251(a); 21 CFR 117.254(a) | AC46: The requirements apply to the storage of unexposed packaged food that requires time/temperature control under Part 117 Subpart D. [1] The establishment must take reasonable measures and precautions to ensure the following: "as appropriate" [9]; "as appropriate" [10]; "as appropriate" [11]; "as appropriate" [12]; "as appropriate" [13]; "as appropriate" [14]; "as appropriate" [20]. [1] | AD46: unmarked | AE46: 46
A47: F-018 | B47: Human Food — 21 CFR 117 | C47: Direct Lookup | D47: Intermediate | E47: How may FDA withdraw a qualified facility exemption under Part 117? | F47: [DRAFT KEY - NOT SME-VERIFIED] Circumstances, order to withdraw, compliance and appeal procedures, reinstatement. | G47: The generated answer could not be validated against the retrieved regulatory evidence, so it is not shown. The retrieved sources were not verified to answer the question as asked, so their text is not quoted as an answer. Sources consulted: 21 CFR 117.10, 21 CFR 117.110(a), 21 CFR 117.126(a), 21 CFR 117.130(a), 21 CFR 117.135(a)(1) and 18 more. | H47: 21 CFR 117.251 et seq. (Subpart E) | I47: none (answer withheld) | J47: no CFR citation | K47: 13.86 | L47: OK | M47: FAIL | O47: No answer delivered: validation withheld the draft. The circumstances in 117.251(a), the order procedure and the appeal and reinstatement route are never given. | P47: Draft key 117.251 et seq. verified correct against the snapshot. || MACHINE CHECKS: indicator: citation vs draft key: no CFR citation | indicator: answer withheld by validation (likely incomplete / no substantive answer) | pipeline validator codes on raw output: provision_citation_mismatch, low_overlap_with_cited_source, invented_condition | Q47: N | R47: 0 | S47: 0 | T47: 0 | U47: 0 | V47: 1 | X47: ANSWERABLE | Y47: unsupported | Z47: mismatched_statements_replaced+failed_repair_fallback | AA47: 21 CFR 117.10; 21 CFR 117.110(a); 21 CFR 117.126(a); 21 CFR 117.130(a); 21 CFR 117.135(a)(1); 21 CFR 117.136(a); 21 CFR 117.137; 21 CFR 117.139; 21 CFR 117.140(a); 21 CFR 117.145; 21 CFR 117.150(a); 21 CFR 117.155(a); 21 CFR 117.160(a); 21 CFR 117.165(a); 21 CFR 117.170(a); 21 CFR 117.180(a); 21 CFR 117.190(a); 21 CFR 117.1(a); 21 CFR 117.201(a); 21 CFR 117.206(a); 21 CFR 117.20(a); 21 CFR 117.251(a); 21 CFR 117.254(a) | AC47: The FDA may withdraw a qualified facility exemption under § 117.254(a) [22]. If applicable, an FDA Division Director in whose division the qualified facility is located (or, in the case of a foreign facility, the Director of the Office of Compliance in the Center for Food Safety and Applied Nutrition), or an FDA official senior to either such Director, must approve an order to withdraw the exemption before the order is issued. [22] | AD47: unmarked | AE47: 47
